Workbook

Sheet Information
A1: Case Study 2: Gasoline versus alternative fuel vehicles (due 4/21, 10 points)
A3: In the Proceedings of the National Academies of Sciences, Michalek et al. (2011) write: The electrification of passenger vehicles has the potential to address three of the most critical challenges of our time - (i) produce fewer greenhouse gas (GHG) emissions when powered by electricity instead of gasoline, depending on the electricity source; (ii) reduce tailpipe emissions, which impact people and the environment; and (iii) reduce gasoline consumption, helping to diminish dependency on imported oil. Recognizing these benefits, US policymakers have provided federal tax credits of up to $7,500 per vehicle to encourage electrified transportation, with additional supporting policies enacted in many states.
A5: Despite the societal benefits conferred by a wider adoption of electrified vehicles, people (like you and me) make decisions based on total ownership costs and pay little attention to environmental and energy security benefits. Therefore, I would like you to estimate total ownership costs for five different vehicle types: (a) conventional gasoline vehicle, (b) alternative fuel (e.g., E85 vehicle) (c) hybrid electric vehicle (HEV), (d) plug-in hybrid electric vehicle (PHEV), and (e) battery electric vehicle (BEV) and explore the uncertainty/variability in the cost estimates using a stochastic model. Total ownership costs should, at a minimum, include costs for the following:
A6: Vehicle and other upfront costs (e.g., auto loan)
A7: Fuel (note: electricity is a ‘fuel’)
A8: Battery (initial and replacement), home charger
A9: Scheduled maintenance (e.g., oil, tire rotation, and other consumables)
A10: Salvage
A11: Local/state/national credit for buying an electric vehicle
A13: The following questions (not exhaustive) should help you get started on the problem:
A14: What type of vehicle should you consider? 4-door sedan? SUV? 2-door coupe? Truck?
A15: Given your choice for a vehicle, what are the costs for a comparable conventional vehicle, alternative fuel vehicle, HEV, PHEV, and BEV? Here, comparable would mean similarity (not equivalence), in say performance, size, functionality, etc.
... A36: Michalek et al., PNAS, 2011: http://www.pnas.org/content/108/40/16554.short

Sheet Calculations
A1: 4-Door Sedan | C1: Upfront Costs
A2: Fuel Type | B2: Specific Vehicle Name/Brand | C2: Purchace Price [$] | D2: Loan Payment | E2: Battery Replacement Cost [$] | F2: Home Charger Cost [$] | G2: Fuel Capacity [gas] | H2: Fuel Capacity [kWh] | I2: Fuel Cost [$/Gal] | J2: Fuel Cost [$/kWh] | K2: Est. Range [miles] | L2: Calc Ann. Fuel Cost | M2: Annual Fuel Cost [$] | N2: Annual Maintenance [$] | O2: Local/State/National Credit [$] | P2: Vehicle Life Span [years] | Q2: Salvage Value [$] | R2: NPV [$]
A3: Gasoline | B3: 2024 Toyota Corolla LE | C3: 22000 | D3: =(C3-O3)*(($B$11)*(1+$B$11)^$B$12)/(((1+$B$11)^$B$12)-1) -> 418.74974 | E3: 112 | F3: 0 | G3: 13.2 | H3: 0 | I3: 3.3 | J3: 0 | K3: 450 | L3: =($B$18/K3)*((G3*I3)+(H3*J3)) -> 1384.24 | M3: 1500 | N3: 500 | O3: 0 | P3: 15 | Q3: 7700 | R3: ='NPV-Gas'!N4 -> -30770.265
A4: E85 | B4: 2024 Chevy Malibu | C4: 28000 | D4: =(C4-O4)*(($B$11)*(1+$B$11)^$B$12)/(((1+$B$11)^$B$12)-1) -> 532.95421 | E4: 112 | F4: 0 | G4: 15.8 | H4: 0 | I4: 2.5 | J4: 0 | K4: 550 | L4: =($B$18/K4)*((G4*I4)+(H4*J4)) -> 1027 | M4: 1800 | N4: 550 | O4: 0 | P4: 15 | Q4: 9800 | R4: ='NPV-E85'!N4 -> -34952.215
A5: HEV | B5: 2024 Honda Accord Hybrid Sport | C5: 32000 | D5: =(C5-O5)*(($B$11)*(1+$B$11)^$B$12)/(((1+$B$11)^$B$12)-1) -> 609.09053 | E5: 220.71 | F5: 1200 | G5: 12.8 | H5: 0 | I5: 3.3 | J5: 0 | K5: 614 | L5: =($B$18/K5)*((G5*I5)+(H5*J5)) -> 983.76547 | M5: 1200 | N5: 600 | O5: 0 | P5: 15 | Q5: 11200 | R5: ='NPV-HEV'!N4 -> -40003.087
A6: PHEV | B6: 2024 Hyundai Sonata Plug-in Hybrid | C6: 34000 | D6: =(C6-O6)*(($B$11)*(1+$B$11)^$B$12)/(((1+$B$11)^$B$12)-1) -> 647.15869 | E6: 6000 | F6: 1140 | G6: 13.2 | H6: 9.8 | I6: 3.3 | J6: 0.15 | K6: 430 | L6: =($B$18/K6)*((G6*I6)+(H6*J6)) -> 1497.5093 | M6: 1000 | N6: 600 | O6: 0 | P6: 15 | Q6: 11900 | R6: ='NPV-PHEV'!N4 -> -44436.33
A7: BEV | B7: 2024 Tesla Model 3 RWD | C7: 39000 | D7: =(C7-O7)*(($B$11)*(1+$B$11)^$B$12)/(((1+$B$11)^$B$12)-1) -> 532.95421 | E7: 15000 | F7: 3000 | G7: 0 | H7: 60 | I7: 0 | J7: 0.15 | K7: 310 | L7: =($B$18/K7)*((G7*I7)+(H7*J7)) -> 415.16129 | M7: 500 | N7: 400 | O7: =B20+B21 -> 11000 | P7: 15 | Q7: 13650 | R7: ='NPV-BEV'!N4 -> -32002.201
A10: Auto Loan Interest | B10: 0.11
A11: Monthly Rate | B11: =B10/12 -> 0.0091666667
A12: Loan Term [months] | B12: 72
A14: Commute [mi/day] | B14: 50
A15: Weekdays Commuted/yr | B15: 250
A16: Weekend Travel [mi] | B16: 100
A17: Weekends Traveled/yr | B17: 18
A18: Annual Miles [mi/yr] | B18: =(B14)*B15+B16*B17 -> 14300
A20: DoE EV Tax Credit | B20: 7500
A21: Colorado EV Tax Credit | B21: 3500
A23: Average MSRPs | B23: =average(C3:C7) -> 31000
A24: Std Dev of MSRPs | B24: =_xlfn.STDEV.S(C3:C7) -> 6403.1242
A25: 1st Quartile (25%) | B25: =QUARTILE(C3:C7,1) -> 28000
A26: 3rd Quartile (75%) | B26: =QUARTILE(C3:C7,3) -> 34000
A28: Colorado Registration Fees | B28: See Table for Calc Method _>
A30: Discount Rate | B30: 0.06

Sheet NPV-Gas
C1: Calculations
E2: 2024 Toyota Corolla LE (GAS)
C3: Year | D3: Month | E3: Loan | F3: Home Charger Install | G3: Fuel Cost | H3: Registration? | I3: Maintenance | J3: New Battery | K3: Salvage | L3: Sum | M3: PV | N3: NPV
A4: Discount Rate? | B4: =Calculations!$B$30 -> 0.06 | C4: 0 | D4: 0 | F4: =-Calculations!F3 -> 0 | L4: =SUM(E4:K4) -> 0 | M4: =L4/(1+$B$4/12)^D4 -> 0 | N4: =sum(M4:M76) -> -30770.265
C5: 1 | D5: 1 | E5: =-Calculations!$D$3 -> -418.74974 | G5: =-Calculations!$L$3/12 -> -115.35333 | H5: =sum(B6:B7) -> -454.07 | L5: =SUM(E5:K5) -> -988.17307 | M5: =L5/(1+$B$4/12)^D5 -> -983.25679
A6: Registration Fees | B6: =-18-23-9-4-0.94-1.5-0.7-2-0.5-1-0.33-0.3-0.1 -> -61.37 | C6: 1 | D6: 2 | E6: =-Calculations!$D$3 -> -418.74974 | G6: =-Calculations!$L$3/12 -> -115.35333 | L6: =SUM(E6:K6) -> -534.10307 | M6: =L6/(1+$B$4/12)^D6 -> -528.80183
A7: SOT Year 1 | B7: =-Calculations!$C$3*0.85*0.021 -> -392.7 | C7: 1 | D7: 3 | E7: =-Calculations!$D$3 -> -418.74974 | G7: =-Calculations!$L$3/12 -> -115.35333 | L7: =SUM(E7:K7) -> -534.10307 | M7: =L7/(1+$B$4/12)^D7 -> -526.17098
A8: SOT Year 2 | B8: =-Calculations!$C$3*0.85*0.015 -> -280.5 | C8: 1 | D8: 4 | E8: =-Calculations!$D$3 -> -418.74974 | G8: =-Calculations!$L$3/12 -> -115.35333 | L8: =SUM(E8:K8) -> -534.10307 | M8: =L8/(1+$B$4/12)^D8 -> -523.55321
A9: SOT Year 3 | B9: =-Calculations!$C$3*0.85*0.012 -> -224.4 | C9: 1 | D9: 5 | E9: =-Calculations!$D$3 -> -418.74974 | G9: =-Calculations!$L$3/12 -> -115.35333 | L9: =SUM(E9:K9) -> -534.10307 | M9: =L9/(1+$B$4/12)^D9 -> -520.94847
A10: SOT Year 4 | B10: =-Calculations!$C$3*0.85*0.009 -> -168.3 | C10: 1 | D10: 6 | E10: =-Calculations!$D$3 -> -418.74974 | G10: =-Calculations!$L$3/12 -> -115.35333 | I10: =-Calculations!$N$3/2 -> -250 | L10: =SUM(E10:K10) -> -784.10307 | M10: =L10/(1+$B$4/12)^D10 -> -760.98621
A11: SOT Year 5 | B11: =-Calculations!$C$3*0.85*0.0045 -> -84.15 | C11: 1 | D11: 7 | E11: =-Calculations!$D$3 -> -418.74974 | G11: =-Calculations!$L$3/12 -> -115.35333 | L11: =SUM(E11:K11) -> -534.10307 | M11: =L11/(1+$B$4/12)^D11 -> -515.7778
A12: SOT Year 6 | B12: =-Calculations!$C$3*0.85*0.0045 -> -84.15 | C12: 1 | D12: 8 | E12: =-Calculations!$D$3 -> -418.74974 | G12: =-Calculations!$L$3/12 -> -115.35333 | L12: =SUM(E12:K12) -> -534.10307 | M12: =L12/(1+$B$4/12)^D12 -> -513.21174
C13: 1 | D13: 9 | E13: =-Calculations!$D$3 -> -418.74974 | G13: =-Calculations!$L$3/12 -> -115.35333 | L13: =SUM(E13:K13) -> -534.10307 | M13: =L13/(1+$B$4/12)^D13 -> -510.65845
C14: 1 | D14: 10 | E14: =-Calculations!$D$3 -> -418.74974 | G14: =-Calculations!$L$3/12 -> -115.35333 | L14: =SUM(E14:K14) -> -534.10307 | M14: =L14/(1+$B$4/12)^D14 -> -508.11786
C15: 1 | D15: 11 | E15: =-Calculations!$D$3 -> -418.74974 | G15: =-Calculations!$L$3/12 -> -115.35333 | L15: =SUM(E15:K15) -> -534.10307 | M15: =L15/(1+$B$4/12)^D15 -> -505.58991
C16: 1 | D16: 12 | E16: =-Calculations!$D$3 -> -418.74974 | G16: =-Calculations!$L$3/12 -> -115.35333 | I16: =-Calculations!$N$3/2 -> -250 | L16: =SUM(E16:K16) -> -784.10307 | M16: =L16/(1+$B$4/12)^D16 -> -738.55087
C17: 2 | D17: 13 | E17: =-Calculations!$D$3 -> -418.74974 | G17: =-Calculations!$L$3/12 -> -115.35333 | H17: =sum(B6,B8) -> -341.87 | L17: =SUM(E17:K17) -> -875.97307 | M17: =L17/(1+$B$4/12)^D17 -> -820.97882
C18: 2 | D18: 14 | E18: =-Calculations!$D$3 -> -418.74974 | G18: =-Calculations!$L$3/12 -> -115.35333 | L18: =SUM(E18:K18) -> -534.10307 | M18: =L18/(1+$B$4/12)^D18 -> -498.08127
C19: 2 | D19: 15 | E19: =-Calculations!$D$3 -> -418.74974 | G19: =-Calculations!$L$3/12 -> -115.35333 | L19: =SUM(E19:K19) -> -534.10307 | M19: =L19/(1+$B$4/12)^D19 -> -495.60325
C20: 2 | D20: 16 | E20: =-Calculations!$D$3 -> -418.74974 | G20: =-Calculations!$L$3/12 -> -115.35333 | L20: =SUM(E20:K20) -> -534.10307 | M20: =L20/(1+$B$4/12)^D20 -> -493.13757
C21: 2 | D21: 17 | E21: =-Calculations!$D$3 -> -418.74974 | G21: =-Calculations!$L$3/12 -> -115.35333 | L21: =SUM(E21:K21) -> -534.10307 | M21: =L21/(1+$B$4/12)^D21 -> -490.68415
C22: 2 | D22: 18 | E22: =-Calculations!$D$3 -> -418.74974 | G22: =-Calculations!$L$3/12 -> -115.35333 | I22: =-Calculations!$N$3/2 -> -250 | L22: =SUM(E22:K22) -> -784.10307 | M22: =L22/(1+$B$4/12)^D22 -> -716.77697
C23: 2 | D23: 19 | E23: =-Calculations!$D$3 -> -418.74974 | G23: =-Calculations!$L$3/12 -> -115.35333 | L23: =SUM(E23:K23) -> -534.10307 | M23: =L23/(1+$B$4/12)^D23 -> -485.81386
C24: 2 | D24: 20 | E24: =-Calculations!$D$3 -> -418.74974 | G24: =-Calculations!$L$3/12 -> -115.35333 | L24: =SUM(E24:K24) -> -534.10307 | M24: =L24/(1+$B$4/12)^D24 -> -483.39688
C25: 2 | D25: 21 | E25: =-Calculations!$D$3 -> -418.74974 | G25: =-Calculations!$L$3/12 -> -115.35333 | L25: =SUM(E25:K25) -> -534.10307 | M25: =L25/(1+$B$4/12)^D25 -> -480.99192
C26: 2 | D26: 22 | E26: =-Calculations!$D$3 -> -418.74974 | G26: =-Calculations!$L$3/12 -> -115.35333 | L26: =SUM(E26:K26) -> -534.10307 | M26: =L26/(1+$B$4/12)^D26 -> -478.59892
C27: 2 | D27: 23 | E27: =-Calculations!$D$3 -> -418.74974 | G27: =-Calculations!$L$3/12 -> -115.35333 | L27: =SUM(E27:K27) -> -534.10307 | M27: =L27/(1+$B$4/12)^D27 -> -476.21783
C28: 2 | D28: 24 | E28: =-Calculations!$D$3 -> -418.74974 | G28: =-Calculations!$L$3/12 -> -115.35333 | I28: =-Calculations!$N$3/2 -> -250 | L28: =SUM(E28:K28) -> -784.10307 | M28: =L28/(1+$B$4/12)^D28 -> -695.64501
C29: 3 | D29: 25 | E29: =-Calculations!$D$3 -> -418.74974 | G29: =-Calculations!$L$3/12 -> -115.35333 | H29: =sum(B9,B6) -> -285.77 | L29: =SUM(E29:K29) -> -819.87307 | M29: =L29/(1+$B$4/12)^D29 -> -723.76084
C30: 3 | D30: 26 | E30: =-Calculations!$D$3 -> -418.74974 | G30: =-Calculations!$L$3/12 -> -115.35333 | L30: =SUM(E30:K30) -> -534.10307 | M30: =L30/(1+$B$4/12)^D30 -> -469.14541
C31: 3 | D31: 27 | E31: =-Calculations!$D$3 -> -418.74974 | G31: =-Calculations!$L$3/12 -> -115.35333 | L31: =SUM(E31:K31) -> -534.10307 | M31: =L31/(1+$B$4/12)^D31 -> -466.81135
C32: 3 | D32: 28 | E32: =-Calculations!$D$3 -> -418.74974 | G32: =-Calculations!$L$3/12 -> -115.35333 | L32: =SUM(E32:K32) -> -534.10307 | M32: =L32/(1+$B$4/12)^D32 -> -464.48891
C33: 3 | D33: 29 | E33: =-Calculations!$D$3 -> -418.74974 | G33: =-Calculations!$L$3/12 -> -115.35333 | L33: =SUM(E33:K33) -> -534.10307 | M33: =L33/(1+$B$4/12)^D33 -> -462.17802
C34: 3 | D34: 30 | E34: =-Calculations!$D$3 -> -418.74974 | G34: =-Calculations!$L$3/12 -> -115.35333 | I34: =-Calculations!$N$3/2 -> -250 | L34: =SUM(E34:K34) -> -784.10307 | M34: =L34/(1+$B$4/12)^D34 -> -675.13606
C35: 3 | D35: 31 | E35: =-Calculations!$D$3 -> -418.74974 | G35: =-Calculations!$L$3/12 -> -115.35333 | L35: =SUM(E35:K35) -> -534.10307 | M35: =L35/(1+$B$4/12)^D35 -> -457.59067
C36: 3 | D36: 32 | E36: =-Calculations!$D$3 -> -418.74974 | G36: =-Calculations!$L$3/12 -> -115.35333 | L36: =SUM(E36:K36) -> -534.10307 | M36: =L36/(1+$B$4/12)^D36 -> -455.3141
C37: 3 | D37: 33 | E37: =-Calculations!$D$3 -> -418.74974 | G37: =-Calculations!$L$3/12 -> -115.35333 | L37: =SUM(E37:K37) -> -534.10307 | M37: =L37/(1+$B$4/12)^D37 -> -453.04886
C38: 3 | D38: 34 | E38: =-Calculations!$D$3 -> -418.74974 | G38: =-Calculations!$L$3/12 -> -115.35333 | L38: =SUM(E38:K38) -> -534.10307 | M38: =L38/(1+$B$4/12)^D38 -> -450.79488
C39: 3 | D39: 35 | E39: =-Calculations!$D$3 -> -418.74974 | G39: =-Calculations!$L$3/12 -> -115.35333 | L39: =SUM(E39:K39) -> -534.10307 | M39: =L39/(1+$B$4/12)^D39 -> -448.55212
C40: 3 | D40: 36 | E40: =-Calculations!$D$3 -> -418.74974 | G40: =-Calculations!$L$3/12 -> -115.35333 | I40: =-Calculations!$N$3/2 -> -250 | L40: =SUM(E40:K40) -> -784.10307 | M40: =L40/(1+$B$4/12)^D40 -> -655.23175
C41: 4 | D41: 37 | E41: =-Calculations!$D$3 -> -418.74974 | G41: =-Calculations!$L$3/12 -> -115.35333 | H41: =sum(B10,B6) -> -229.67 | L41: =SUM(E41:K41) -> -763.77307 | M41: =L41/(1+$B$4/12)^D41 -> -635.06775
C42: 4 | D42: 38 | E42: =-Calculations!$D$3 -> -418.74974 | G42: =-Calculations!$L$3/12 -> -115.35333 | L42: =SUM(E42:K42) -> -534.10307 | M42: =L42/(1+$B$4/12)^D42 -> -441.89056
C43: 4 | D43: 39 | E43: =-Calculations!$D$3 -> -418.74974 | G43: =-Calculations!$L$3/12 -> -115.35333 | L43: =SUM(E43:K43) -> -534.10307 | M43: =L43/(1+$B$4/12)^D43 -> -439.6921
C44: 4 | D44: 40 | E44: =-Calculations!$D$3 -> -418.74974 | G44: =-Calculations!$L$3/12 -> -115.35333 | L44: =SUM(E44:K44) -> -534.10307 | M44: =L44/(1+$B$4/12)^D44 -> -437.50458
C45: 4 | D45: 41 | E45: =-Calculations!$D$3 -> -418.74974 | G45: =-Calculations!$L$3/12 -> -115.35333 | L45: =SUM(E45:K45) -> -534.10307 | M45: =L45/(1+$B$4/12)^D45 -> -435.32794
C46: 4 | D46: 42 | E46: =-Calculations!$D$3 -> -418.74974 | G46: =-Calculations!$L$3/12 -> -115.35333 | I46: =-Calculations!$N$3/2 -> -250 | L46: =SUM(E46:K46) -> -784.10307 | M46: =L46/(1+$B$4/12)^D46 -> -635.91426
C47: 4 | D47: 43 | E47: =-Calculations!$D$3 -> -418.74974 | G47: =-Calculations!$L$3/12 -> -115.35333 | L47: =SUM(E47:K47) -> -534.10307 | M47: =L47/(1+$B$4/12)^D47 -> -431.0071
C48: 4 | D48: 44 | E48: =-Calculations!$D$3 -> -418.74974 | G48: =-Calculations!$L$3/12 -> -115.35333 | L48: =SUM(E48:K48) -> -534.10307 | M48: =L48/(1+$B$4/12)^D48 -> -428.86278
C49: 4 | D49: 45 | E49: =-Calculations!$D$3 -> -418.74974 | G49: =-Calculations!$L$3/12 -> -115.35333 | L49: =SUM(E49:K49) -> -534.10307 | M49: =L49/(1+$B$4/12)^D49 -> -426.72914
C50: 4 | D50: 46 | E50: =-Calculations!$D$3 -> -418.74974 | G50: =-Calculations!$L$3/12 -> -115.35333 | L50: =SUM(E50:K50) -> -534.10307 | M50: =L50/(1+$B$4/12)^D50 -> -424.60611
C51: 4 | D51: 47 | E51: =-Calculations!$D$3 -> -418.74974 | G51: =-Calculations!$L$3/12 -> -115.35333 | L51: =SUM(E51:K51) -> -534.10307 | M51: =L51/(1+$B$4/12)^D51 -> -422.49364
C52: 4 | D52: 48 | E52: =-Calculations!$D$3 -> -418.74974 | G52: =-Calculations!$L$3/12 -> -115.35333 | I52: =-Calculations!$N$3/2 -> -250 | L52: =SUM(E52:K52) -> -784.10307 | M52: =L52/(1+$B$4/12)^D52 -> -617.16628
C53: 5 | D53: 49 | E53: =-Calculations!$D$3 -> -418.74974 | G53: =-Calculations!$L$3/12 -> -115.35333 | H53: =sum(B11,B6) -> -145.52 | L53: =SUM(E53:K53) -> -679.62307 | M53: =L53/(1+$B$4/12)^D53 -> -532.2689
C54: 5 | D54: 50 | E54: =-Calculations!$D$3 -> -418.74974 | G54: =-Calculations!$L$3/12 -> -115.35333 | L54: =SUM(E54:K54) -> -534.10307 | M54: =L54/(1+$B$4/12)^D54 -> -416.21908
C55: 5 | D55: 51 | E55: =-Calculations!$D$3 -> -418.74974 | G55: =-Calculations!$L$3/12 -> -115.35333 | L55: =SUM(E55:K55) -> -534.10307 | M55: =L55/(1+$B$4/12)^D55 -> -414.14834
C56: 5 | D56: 52 | E56: =-Calculations!$D$3 -> -418.74974 | G56: =-Calculations!$L$3/12 -> -115.35333 | L56: =SUM(E56:K56) -> -534.10307 | M56: =L56/(1+$B$4/12)^D56 -> -412.0879
C57: 5 | D57: 53 | E57: =-Calculations!$D$3 -> -418.74974 | G57: =-Calculations!$L$3/12 -> -115.35333 | L57: =SUM(E57:K57) -> -534.10307 | M57: =L57/(1+$B$4/12)^D57 -> -410.03771
C58: 5 | D58: 54 | E58: =-Calculations!$D$3 -> -418.74974 | G58: =-Calculations!$L$3/12 -> -115.35333 | I58: =-Calculations!$N$3/2 -> -250 | L58: =SUM(E58:K58) -> -784.10307 | M58: =L58/(1+$B$4/12)^D58 -> -598.97103
C59: 5 | D59: 55 | E59: =-Calculations!$D$3 -> -418.74974 | G59: =-Calculations!$L$3/12 -> -115.35333 | L59: =SUM(E59:K59) -> -534.10307 | M59: =L59/(1+$B$4/12)^D59 -> -405.96788
C60: 5 | D60: 56 | E60: =-Calculations!$D$3 -> -418.74974 | G60: =-Calculations!$L$3/12 -> -115.35333 | L60: =SUM(E60:K60) -> -534.10307 | M60: =L60/(1+$B$4/12)^D60 -> -403.94814
C61: 5 | D61: 57 | E61: =-Calculations!$D$3 -> -418.74974 | G61: =-Calculations!$L$3/12 -> -115.35333 | L61: =SUM(E61:K61) -> -534.10307 | M61: =L61/(1+$B$4/12)^D61 -> -401.93845
C62: 5 | D62: 58 | E62: =-Calculations!$D$3 -> -418.74974 | G62: =-Calculations!$L$3/12 -> -115.35333 | L62: =SUM(E62:K62) -> -534.10307 | M62: =L62/(1+$B$4/12)^D62 -> -399.93876
C63: 5 | D63: 59 | E63: =-Calculations!$D$3 -> -418.74974 | G63: =-Calculations!$L$3/12 -> -115.35333 | L63: =SUM(E63:K63) -> -534.10307 | M63: =L63/(1+$B$4/12)^D63 -> -397.94901
C64: 5 | D64: 60 | E64: =-Calculations!$D$3 -> -418.74974 | G64: =-Calculations!$L$3/12 -> -115.35333 | I64: =-Calculations!$N$3/2 -> -250 | L64: =SUM(E64:K64) -> -784.10307 | M64: =L64/(1+$B$4/12)^D64 -> -581.31222
C65: 6 | D65: 61 | E65: =-Calculations!$D$3 -> -418.74974 | G65: =-Calculations!$L$3/12 -> -115.35333 | H65: =sum(B12,B6) -> -145.52 | L65: =SUM(E65:K65) -> -679.62307 | M65: =L65/(1+$B$4/12)^D65 -> -501.34691
C66: 6 | D66: 62 | E66: =-Calculations!$D$3 -> -418.74974 | G66: =-Calculations!$L$3/12 -> -115.35333 | L66: =SUM(E66:K66) -> -534.10307 | M66: =L66/(1+$B$4/12)^D66 -> -392.03898
C67: 6 | D67: 63 | E67: =-Calculations!$D$3 -> -418.74974 | G67: =-Calculations!$L$3/12 -> -115.35333 | L67: =SUM(E67:K67) -> -534.10307 | M67: =L67/(1+$B$4/12)^D67 -> -390.08853
C68: 6 | D68: 64 | E68: =-Calculations!$D$3 -> -418.74974 | G68: =-Calculations!$L$3/12 -> -115.35333 | L68: =SUM(E68:K68) -> -534.10307 | M68: =L68/(1+$B$4/12)^D68 -> -388.14779
C69: 6 | D69: 65 | E69: =-Calculations!$D$3 -> -418.74974 | G69: =-Calculations!$L$3/12 -> -115.35333 | L69: =SUM(E69:K69) -> -534.10307 | M69: =L69/(1+$B$4/12)^D69 -> -386.21671
C70: 6 | D70: 66 | E70: =-Calculations!$D$3 -> -418.74974 | G70: =-Calculations!$L$3/12 -> -115.35333 | I70: =-Calculations!$N$3/2 -> -250 | L70: =SUM(E70:K70) -> -784.10307 | M70: =L70/(1+$B$4/12)^D70 -> -564.17401
C71: 6 | D71: 67 | E71: =-Calculations!$D$3 -> -418.74974 | G71: =-Calculations!$L$3/12 -> -115.35333 | L71: =SUM(E71:K71) -> -534.10307 | M71: =L71/(1+$B$4/12)^D71 -> -382.38332
C72: 6 | D72: 68 | E72: =-Calculations!$D$3 -> -418.74974 | G72: =-Calculations!$L$3/12 -> -115.35333 | L72: =SUM(E72:K72) -> -534.10307 | M72: =L72/(1+$B$4/12)^D72 -> -380.48091
C73: 6 | D73: 69 | E73: =-Calculations!$D$3 -> -418.74974 | G73: =-Calculations!$L$3/12 -> -115.35333 | L73: =SUM(E73:K73) -> -534.10307 | M73: =L73/(1+$B$4/12)^D73 -> -378.58797
C74: 6 | D74: 70 | E74: =-Calculations!$D$3 -> -418.74974 | G74: =-Calculations!$L$3/12 -> -115.35333 | L74: =SUM(E74:K74) -> -534.10307 | M74: =L74/(1+$B$4/12)^D74 -> -376.70445
C75: 6 | D75: 71 | E75: =-Calculations!$D$3 -> -418.74974 | G75: =-Calculations!$L$3/12 -> -115.35333 | L75: =SUM(E75:K75) -> -534.10307 | M75: =L75/(1+$B$4/12)^D75 -> -374.8303
C76: 6 | D76: 72 | E76: =-Calculations!$D$3 -> -418.74974 | G76: =-Calculations!$L$3/12 -> -115.35333 | I76: =-Calculations!$N$3/2 -> -250 | K76: =Calculations!Q3 -> 7700 | L76: =SUM(E76:K76) -> 6915.8969 | M76: =L76/(1+$B$4/12)^D76 -> 4829.3876

Sheet NPV-E85
C1: Calculations
E2: 2024 Chevy Malibu (E85)
C3: Year | D3: Month | E3: Loan | F3: Home Charger Install | G3: Fuel Cost | H3: Registration? | I3: Maintenance | J3: New Battery | K3: Salvage | L3: Sum | M3: PV | N3: NPV
A4: Discount Rate? | B4: =Calculations!$B$30 -> 0.06 | C4: 0 | D4: 0 | F4: =-Calculations!F4 -> 0 | L4: =SUM(E4:K4) -> 0 | M4: =L4/(1+$B$4/12)^D4 -> 0 | N4: =sum(M4:M76) -> -34952.215
C5: 1 | D5: 1 | E5: =-Calculations!$D$4 -> -532.95421 | G5: =-Calculations!$L$4/12 -> -85.583333 | H5: =sum(B6:B7) -> -561.17 | L5: =SUM(E5:K5) -> -1179.7075 | M5: =L5/(1+$B$4/12)^D5 -> -1173.8384
A6: Registration Fees | B6: =-18-23-9-4-0.94-1.5-0.7-2-0.5-1-0.33-0.3-0.1 -> -61.37 | C6: 1 | D6: 2 | E6: =-Calculations!$D$4 -> -532.95421 | G6: =-Calculations!$L$4/12 -> -85.583333 | L6: =SUM(E6:K6) -> -618.53755 | M6: =L6/(1+$B$4/12)^D6 -> -612.39825
A7: SOT Year 1 | B7: =-Calculations!$C$4*0.85*0.021 -> -499.8 | C7: 1 | D7: 3 | E7: =-Calculations!$D$4 -> -532.95421 | G7: =-Calculations!$L$4/12 -> -85.583333 | L7: =SUM(E7:K7) -> -618.53755 | M7: =L7/(1+$B$4/12)^D7 -> -609.3515
A8: SOT Year 2 | B8: =-Calculations!$C$4*0.85*0.015 -> -357 | C8: 1 | D8: 4 | E8: =-Calculations!$D$4 -> -532.95421 | G8: =-Calculations!$L$4/12 -> -85.583333 | L8: =SUM(E8:K8) -> -618.53755 | M8: =L8/(1+$B$4/12)^D8 -> -606.3199
A9: SOT Year 3 | B9: =-Calculations!$C$4*0.85*0.012 -> -285.6 | C9: 1 | D9: 5 | E9: =-Calculations!$D$4 -> -532.95421 | G9: =-Calculations!$L$4/12 -> -85.583333 | L9: =SUM(E9:K9) -> -618.53755 | M9: =L9/(1+$B$4/12)^D9 -> -603.30338
A10: SOT Year 4 | B10: =-Calculations!$C$4*0.85*0.009 -> -214.2 | C10: 1 | D10: 6 | E10: =-Calculations!$D$4 -> -532.95421 | G10: =-Calculations!$L$4/12 -> -85.583333 | I10: =-Calculations!$N$4/2 -> -275 | L10: =SUM(E10:K10) -> -893.53755 | M10: =L10/(1+$B$4/12)^D10 -> -867.19434
A11: SOT Year 5 | B11: =-Calculations!$C$4*0.85*0.0045 -> -107.1 | C11: 1 | D11: 7 | E11: =-Calculations!$D$4 -> -532.95421 | G11: =-Calculations!$L$4/12 -> -85.583333 | L11: =SUM(E11:K11) -> -618.53755 | M11: =L11/(1+$B$4/12)^D11 -> -597.31529
A12: SOT Year 6 | B12: =-Calculations!$C$4*0.85*0.0045 -> -107.1 | C12: 1 | D12: 8 | E12: =-Calculations!$D$4 -> -532.95421 | G12: =-Calculations!$L$4/12 -> -85.583333 | L12: =SUM(E12:K12) -> -618.53755 | M12: =L12/(1+$B$4/12)^D12 -> -594.34358
C13: 1 | D13: 9 | E13: =-Calculations!$D$4 -> -532.95421 | G13: =-Calculations!$L$4/12 -> -85.583333 | L13: =SUM(E13:K13) -> -618.53755 | M13: =L13/(1+$B$4/12)^D13 -> -591.38664
C14: 1 | D14: 10 | E14: =-Calculations!$D$4 -> -532.95421 | G14: =-Calculations!$L$4/12 -> -85.583333 | L14: =SUM(E14:K14) -> -618.53755 | M14: =L14/(1+$B$4/12)^D14 -> -588.44442
C15: 1 | D15: 11 | E15: =-Calculations!$D$4 -> -532.95421 | G15: =-Calculations!$L$4/12 -> -85.583333 | L15: =SUM(E15:K15) -> -618.53755 | M15: =L15/(1+$B$4/12)^D15 -> -585.51684
C16: 1 | D16: 12 | E16: =-Calculations!$D$4 -> -532.95421 | G16: =-Calculations!$L$4/12 -> -85.583333 | I16: =-Calculations!$N$4/2 -> -275 | L16: =SUM(E16:K16) -> -893.53755 | M16: =L16/(1+$B$4/12)^D16 -> -841.62779
C17: 2 | D17: 13 | E17: =-Calculations!$D$4 -> -532.95421 | G17: =-Calculations!$L$4/12 -> -85.583333 | H17: =sum(B6,B8) -> -418.37 | L17: =SUM(E17:K17) -> -1036.9075 | M17: =L17/(1+$B$4/12)^D17 -> -971.80971
C18: 2 | D18: 14 | E18: =-Calculations!$D$4 -> -532.95421 | G18: =-Calculations!$L$4/12 -> -85.583333 | L18: =SUM(E18:K18) -> -618.53755 | M18: =L18/(1+$B$4/12)^D18 -> -576.82118
C19: 2 | D19: 15 | E19: =-Calculations!$D$4 -> -532.95421 | G19: =-Calculations!$L$4/12 -> -85.583333 | L19: =SUM(E19:K19) -> -618.53755 | M19: =L19/(1+$B$4/12)^D19 -> -573.95143
C20: 2 | D20: 16 | E20: =-Calculations!$D$4 -> -532.95421 | G20: =-Calculations!$L$4/12 -> -85.583333 | L20: =SUM(E20:K20) -> -618.53755 | M20: =L20/(1+$B$4/12)^D20 -> -571.09595
C21: 2 | D21: 17 | E21: =-Calculations!$D$4 -> -532.95421 | G21: =-Calculations!$L$4/12 -> -85.583333 | L21: =SUM(E21:K21) -> -618.53755 | M21: =L21/(1+$B$4/12)^D21 -> -568.25467
C22: 2 | D22: 18 | E22: =-Calculations!$D$4 -> -532.95421 | G22: =-Calculations!$L$4/12 -> -85.583333 | I22: =-Calculations!$N$4/2 -> -275 | L22: =SUM(E22:K22) -> -893.53755 | M22: =L22/(1+$B$4/12)^D22 -> -816.81498
C23: 2 | D23: 19 | E23: =-Calculations!$D$4 -> -532.95421 | G23: =-Calculations!$L$4/12 -> -85.583333 | L23: =SUM(E23:K23) -> -618.53755 | M23: =L23/(1+$B$4/12)^D23 -> -562.61446
C24: 2 | D24: 20 | E24: =-Calculations!$D$4 -> -532.95421 | G24: =-Calculations!$L$4/12 -> -85.583333 | L24: =SUM(E24:K24) -> -618.53755 | M24: =L24/(1+$B$4/12)^D24 -> -559.81539
C25: 2 | D25: 21 | E25: =-Calculations!$D$4 -> -532.95421 | G25: =-Calculations!$L$4/12 -> -85.583333 | L25: =SUM(E25:K25) -> -618.53755 | M25: =L25/(1+$B$4/12)^D25 -> -557.03024
C26: 2 | D26: 22 | E26: =-Calculations!$D$4 -> -532.95421 | G26: =-Calculations!$L$4/12 -> -85.583333 | L26: =SUM(E26:K26) -> -618.53755 | M26: =L26/(1+$B$4/12)^D26 -> -554.25894
C27: 2 | D27: 23 | E27: =-Calculations!$D$4 -> -532.95421 | G27: =-Calculations!$L$4/12 -> -85.583333 | L27: =SUM(E27:K27) -> -618.53755 | M27: =L27/(1+$B$4/12)^D27 -> -551.50143
C28: 2 | D28: 24 | E28: =-Calculations!$D$4 -> -532.95421 | G28: =-Calculations!$L$4/12 -> -85.583333 | I28: =-Calculations!$N$4/2 -> -275 | L28: =SUM(E28:K28) -> -893.53755 | M28: =L28/(1+$B$4/12)^D28 -> -792.7337
C29: 3 | D29: 25 | E29: =-Calculations!$D$4 -> -532.95421 | G29: =-Calculations!$L$4/12 -> -85.583333 | H29: =sum(B9,B6) -> -346.97 | L29: =SUM(E29:K29) -> -965.50755 | M29: =L29/(1+$B$4/12)^D29 -> -852.32284
C30: 3 | D30: 26 | E30: =-Calculations!$D$4 -> -532.95421 | G30: =-Calculations!$L$4/12 -> -85.583333 | L30: =SUM(E30:K30) -> -618.53755 | M30: =L30/(1+$B$4/12)^D30 -> -543.31095
C31: 3 | D31: 27 | E31: =-Calculations!$D$4 -> -532.95421 | G31: =-Calculations!$L$4/12 -> -85.583333 | L31: =SUM(E31:K31) -> -618.53755 | M31: =L31/(1+$B$4/12)^D31 -> -540.60791
C32: 3 | D32: 28 | E32: =-Calculations!$D$4 -> -532.95421 | G32: =-Calculations!$L$4/12 -> -85.583333 | L32: =SUM(E32:K32) -> -618.53755 | M32: =L32/(1+$B$4/12)^D32 -> -537.91832
C33: 3 | D33: 29 | E33: =-Calculations!$D$4 -> -532.95421 | G33: =-Calculations!$L$4/12 -> -85.583333 | L33: =SUM(E33:K33) -> -618.53755 | M33: =L33/(1+$B$4/12)^D33 -> -535.24211
C34: 3 | D34: 30 | E34: =-Calculations!$D$4 -> -532.95421 | G34: =-Calculations!$L$4/12 -> -85.583333 | I34: =-Calculations!$N$4/2 -> -275 | L34: =SUM(E34:K34) -> -893.53755 | M34: =L34/(1+$B$4/12)^D34 -> -769.36239
C35: 3 | D35: 31 | E35: =-Calculations!$D$4 -> -532.95421 | G35: =-Calculations!$L$4/12 -> -85.583333 | L35: =SUM(E35:K35) -> -618.53755 | M35: =L35/(1+$B$4/12)^D35 -> -529.92957
C36: 3 | D36: 32 | E36: =-Calculations!$D$4 -> -532.95421 | G36: =-Calculations!$L$4/12 -> -85.583333 | L36: =SUM(E36:K36) -> -618.53755 | M36: =L36/(1+$B$4/12)^D36 -> -527.2931
C37: 3 | D37: 33 | E37: =-Calculations!$D$4 -> -532.95421 | G37: =-Calculations!$L$4/12 -> -85.583333 | L37: =SUM(E37:K37) -> -618.53755 | M37: =L37/(1+$B$4/12)^D37 -> -524.66975
C38: 3 | D38: 34 | E38: =-Calculations!$D$4 -> -532.95421 | G38: =-Calculations!$L$4/12 -> -85.583333 | L38: =SUM(E38:K38) -> -618.53755 | M38: =L38/(1+$B$4/12)^D38 -> -522.05946
C39: 3 | D39: 35 | E39: =-Calculations!$D$4 -> -532.95421 | G39: =-Calculations!$L$4/12 -> -85.583333 | L39: =SUM(E39:K39) -> -618.53755 | M39: =L39/(1+$B$4/12)^D39 -> -519.46215
C40: 3 | D40: 36 | E40: =-Calculations!$D$4 -> -532.95421 | G40: =-Calculations!$L$4/12 -> -85.583333 | I40: =-Calculations!$N$4/2 -> -275 | L40: =SUM(E40:K40) -> -893.53755 | M40: =L40/(1+$B$4/12)^D40 -> -746.68011
C41: 4 | D41: 37 | E41: =-Calculations!$D$4 -> -532.95421 | G41: =-Calculations!$L$4/12 -> -85.583333 | H41: =sum(B10,B6) -> -275.57 | L41: =SUM(E41:K41) -> -894.10755 | M41: =L41/(1+$B$4/12)^D41 -> -743.43923
C42: 4 | D42: 38 | E42: =-Calculations!$D$4 -> -532.95421 | G42: =-Calculations!$L$4/12 -> -85.583333 | L42: =SUM(E42:K42) -> -618.53755 | M42: =L42/(1+$B$4/12)^D42 -> -511.74749
C43: 4 | D43: 39 | E43: =-Calculations!$D$4 -> -532.95421 | G43: =-Calculations!$L$4/12 -> -85.583333 | L43: =SUM(E43:K43) -> -618.53755 | M43: =L43/(1+$B$4/12)^D43 -> -509.20148
C44: 4 | D44: 40 | E44: =-Calculations!$D$4 -> -532.95421 | G44: =-Calculations!$L$4/12 -> -85.583333 | L44: =SUM(E44:K44) -> -618.53755 | M44: =L44/(1+$B$4/12)^D44 -> -506.66814
C45: 4 | D45: 41 | E45: =-Calculations!$D$4 -> -532.95421 | G45: =-Calculations!$L$4/12 -> -85.583333 | L45: =SUM(E45:K45) -> -618.53755 | M45: =L45/(1+$B$4/12)^D45 -> -504.1474
C46: 4 | D46: 42 | E46: =-Calculations!$D$4 -> -532.95421 | G46: =-Calculations!$L$4/12 -> -85.583333 | I46: =-Calculations!$N$4/2 -> -275 | L46: =SUM(E46:K46) -> -893.53755 | M46: =L46/(1+$B$4/12)^D46 -> -724.66654
C47: 4 | D47: 43 | E47: =-Calculations!$D$4 -> -532.95421 | G47: =-Calculations!$L$4/12 -> -85.583333 | L47: =SUM(E47:K47) -> -618.53755 | M47: =L47/(1+$B$4/12)^D47 -> -499.14349
C48: 4 | D48: 44 | E48: =-Calculations!$D$4 -> -532.95421 | G48: =-Calculations!$L$4/12 -> -85.583333 | L48: =SUM(E48:K48) -> -618.53755 | M48: =L48/(1+$B$4/12)^D48 -> -496.66019
C49: 4 | D49: 45 | E49: =-Calculations!$D$4 -> -532.95421 | G49: =-Calculations!$L$4/12 -> -85.583333 | L49: =SUM(E49:K49) -> -618.53755 | M49: =L49/(1+$B$4/12)^D49 -> -494.18924
C50: 4 | D50: 46 | E50: =-Calculations!$D$4 -> -532.95421 | G50: =-Calculations!$L$4/12 -> -85.583333 | L50: =SUM(E50:K50) -> -618.53755 | M50: =L50/(1+$B$4/12)^D50 -> -491.73059
C51: 4 | D51: 47 | E51: =-Calculations!$D$4 -> -532.95421 | G51: =-Calculations!$L$4/12 -> -85.583333 | L51: =SUM(E51:K51) -> -618.53755 | M51: =L51/(1+$B$4/12)^D51 -> -489.28417
C52: 4 | D52: 48 | E52: =-Calculations!$D$4 -> -532.95421 | G52: =-Calculations!$L$4/12 -> -85.583333 | I52: =-Calculations!$N$4/2 -> -275 | L52: =SUM(E52:K52) -> -893.53755 | M52: =L52/(1+$B$4/12)^D52 -> -703.30198
C53: 5 | D53: 49 | E53: =-Calculations!$D$4 -> -532.95421 | G53: =-Calculations!$L$4/12 -> -85.583333 | H53: =sum(B11,B6) -> -168.47 | L53: =SUM(E53:K53) -> -787.00755 | M53: =L53/(1+$B$4/12)^D53 -> -616.37054
C54: 5 | D54: 50 | E54: =-Calculations!$D$4 -> -532.95421 | G54: =-Calculations!$L$4/12 -> -85.583333 | L54: =SUM(E54:K54) -> -618.53755 | M54: =L54/(1+$B$4/12)^D54 -> -482.01769
C55: 5 | D55: 51 | E55: =-Calculations!$D$4 -> -532.95421 | G55: =-Calculations!$L$4/12 -> -85.583333 | L55: =SUM(E55:K55) -> -618.53755 | M55: =L55/(1+$B$4/12)^D55 -> -479.61959
C56: 5 | D56: 52 | E56: =-Calculations!$D$4 -> -532.95421 | G56: =-Calculations!$L$4/12 -> -85.583333 | L56: =SUM(E56:K56) -> -618.53755 | M56: =L56/(1+$B$4/12)^D56 -> -477.23343
C57: 5 | D57: 53 | E57: =-Calculations!$D$4 -> -532.95421 | G57: =-Calculations!$L$4/12 -> -85.583333 | L57: =SUM(E57:K57) -> -618.53755 | M57: =L57/(1+$B$4/12)^D57 -> -474.85913
C58: 5 | D58: 54 | E58: =-Calculations!$D$4 -> -532.95421 | G58: =-Calculations!$L$4/12 -> -85.583333 | I58: =-Calculations!$N$4/2 -> -275 | L58: =SUM(E58:K58) -> -893.53755 | M58: =L58/(1+$B$4/12)^D58 -> -682.56729
C59: 5 | D59: 55 | E59: =-Calculations!$D$4 -> -532.95421 | G59: =-Calculations!$L$4/12 -> -85.583333 | L59: =SUM(E59:K59) -> -618.53755 | M59: =L59/(1+$B$4/12)^D59 -> -470.14592
C60: 5 | D60: 56 | E60: =-Calculations!$D$4 -> -532.95421 | G60: =-Calculations!$L$4/12 -> -85.583333 | L60: =SUM(E60:K60) -> -618.53755 | M60: =L60/(1+$B$4/12)^D60 -> -467.80688
C61: 5 | D61: 57 | E61: =-Calculations!$D$4 -> -532.95421 | G61: =-Calculations!$L$4/12 -> -85.583333 | L61: =SUM(E61:K61) -> -618.53755 | M61: =L61/(1+$B$4/12)^D61 -> -465.47949
C62: 5 | D62: 58 | E62: =-Calculations!$D$4 -> -532.95421 | G62: =-Calculations!$L$4/12 -> -85.583333 | L62: =SUM(E62:K62) -> -618.53755 | M62: =L62/(1+$B$4/12)^D62 -> -463.16367
C63: 5 | D63: 59 | E63: =-Calculations!$D$4 -> -532.95421 | G63: =-Calculations!$L$4/12 -> -85.583333 | L63: =SUM(E63:K63) -> -618.53755 | M63: =L63/(1+$B$4/12)^D63 -> -460.85937
C64: 5 | D64: 60 | E64: =-Calculations!$D$4 -> -532.95421 | G64: =-Calculations!$L$4/12 -> -85.583333 | I64: =-Calculations!$N$4/2 -> -275 | L64: =SUM(E64:K64) -> -893.53755 | M64: =L64/(1+$B$4/12)^D64 -> -662.44389
C65: 6 | D65: 61 | E65: =-Calculations!$D$4 -> -532.95421 | G65: =-Calculations!$L$4/12 -> -85.583333 | H65: =sum(B12,B6) -> -168.47 | L65: =SUM(E65:K65) -> -787.00755 | M65: =L65/(1+$B$4/12)^D65 -> -580.5627
C66: 6 | D66: 62 | E66: =-Calculations!$D$4 -> -532.95421 | G66: =-Calculations!$L$4/12 -> -85.583333 | L66: =SUM(E66:K66) -> -618.53755 | M66: =L66/(1+$B$4/12)^D66 -> -454.01504
C67: 6 | D67: 63 | E67: =-Calculations!$D$4 -> -532.95421 | G67: =-Calculations!$L$4/12 -> -85.583333 | L67: =SUM(E67:K67) -> -618.53755 | M67: =L67/(1+$B$4/12)^D67 -> -451.75626
C68: 6 | D68: 64 | E68: =-Calculations!$D$4 -> -532.95421 | G68: =-Calculations!$L$4/12 -> -85.583333 | L68: =SUM(E68:K68) -> -618.53755 | M68: =L68/(1+$B$4/12)^D68 -> -449.50871
C69: 6 | D69: 65 | E69: =-Calculations!$D$4 -> -532.95421 | G69: =-Calculations!$L$4/12 -> -85.583333 | L69: =SUM(E69:K69) -> -618.53755 | M69: =L69/(1+$B$4/12)^D69 -> -447.27235
C70: 6 | D70: 66 | E70: =-Calculations!$D$4 -> -532.95421 | G70: =-Calculations!$L$4/12 -> -85.583333 | I70: =-Calculations!$N$4/2 -> -275 | L70: =SUM(E70:K70) -> -893.53755 | M70: =L70/(1+$B$4/12)^D70 -> -642.91377
C71: 6 | D71: 67 | E71: =-Calculations!$D$4 -> -532.95421 | G71: =-Calculations!$L$4/12 -> -85.583333 | L71: =SUM(E71:K71) -> -618.53755 | M71: =L71/(1+$B$4/12)^D71 -> -442.83295
C72: 6 | D72: 68 | E72: =-Calculations!$D$4 -> -532.95421 | G72: =-Calculations!$L$4/12 -> -85.583333 | L72: =SUM(E72:K72) -> -618.53755 | M72: =L72/(1+$B$4/12)^D72 -> -440.6298
C73: 6 | D73: 69 | E73: =-Calculations!$D$4 -> -532.95421 | G73: =-Calculations!$L$4/12 -> -85.583333 | L73: =SUM(E73:K73) -> -618.53755 | M73: =L73/(1+$B$4/12)^D73 -> -438.43761
C74: 6 | D74: 70 | E74: =-Calculations!$D$4 -> -532.95421 | G74: =-Calculations!$L$4/12 -> -85.583333 | L74: =SUM(E74:K74) -> -618.53755 | M74: =L74/(1+$B$4/12)^D74 -> -436.25633
C75: 6 | D75: 71 | E75: =-Calculations!$D$4 -> -532.95421 | G75: =-Calculations!$L$4/12 -> -85.583333 | L75: =SUM(E75:K75) -> -618.53755 | M75: =L75/(1+$B$4/12)^D75 -> -434.0859
C76: 6 | D76: 72 | E76: =-Calculations!$D$4 -> -532.95421 | G76: =-Calculations!$L$4/12 -> -85.583333 | I76: =-Calculations!$N$4/2 -> -275 | K76: =Calculations!Q4 -> 9800 | L76: =SUM(E76:K76) -> 8906.4625 | M76: =L76/(1+$B$4/12)^D76 -> 6219.4044

Sheet NPV-HEV
C1: Calculations
E2: 2024 Honda Accord Hybrid Sport (HEV)
C3: Year | D3: Month | E3: Loan | F3: Home Charger Install | G3: Fuel Cost | H3: Registration? | I3: Maintenance | J3: New Battery | K3: Salvage | L3: Sum | M3: PV | N3: NPV
A4: Discount Rate? | B4: =Calculations!$B$30 -> 0.06 | C4: 0 | D4: 0 | F4: =-Calculations!F5 -> -1200 | L4: =SUM(E4:K4) -> -1200 | M4: =L4/(1+$B$4/12)^D4 -> -1200 | N4: =sum(M4:M76) -> -40003.087
C5: 1 | D5: 1 | E5: =-Calculations!$D$5 -> -609.09053 | G5: =-Calculations!$L$5/12 -> -81.980456 | H5: =sum(B6:B7) -> -632.57 | L5: =SUM(E5:K5) -> -1323.641 | M5: =L5/(1+$B$4/12)^D5 -> -1317.0557
A6: Registration Fees | B6: =-18-23-9-4-0.94-1.5-0.7-2-0.5-1-0.33-0.3-0.1 -> -61.37 | C6: 1 | D6: 2 | E6: =-Calculations!$D$5 -> -609.09053 | G6: =-Calculations!$L$5/12 -> -81.980456 | L6: =SUM(E6:K6) -> -691.07098 | M6: =L6/(1+$B$4/12)^D6 -> -684.21176
A7: SOT Year 1 | B7: =-Calculations!$C$5*0.85*0.021 -> -571.2 | C7: 1 | D7: 3 | E7: =-Calculations!$D$5 -> -609.09053 | G7: =-Calculations!$L$5/12 -> -81.980456 | L7: =SUM(E7:K7) -> -691.07098 | M7: =L7/(1+$B$4/12)^D7 -> -680.80772
A8: SOT Year 2 | B8: =-Calculations!$C$5*0.85*0.015 -> -408 | C8: 1 | D8: 4 | E8: =-Calculations!$D$5 -> -609.09053 | G8: =-Calculations!$L$5/12 -> -81.980456 | L8: =SUM(E8:K8) -> -691.07098 | M8: =L8/(1+$B$4/12)^D8 -> -677.42062
A9: SOT Year 3 | B9: =-Calculations!$C$5*0.85*0.012 -> -326.4 | C9: 1 | D9: 5 | E9: =-Calculations!$D$5 -> -609.09053 | G9: =-Calculations!$L$5/12 -> -81.980456 | L9: =SUM(E9:K9) -> -691.07098 | M9: =L9/(1+$B$4/12)^D9 -> -674.05037
A10: SOT Year 4 | B10: =-Calculations!$C$5*0.85*0.009 -> -244.8 | C10: 1 | D10: 6 | E10: =-Calculations!$D$5 -> -609.09053 | G10: =-Calculations!$L$5/12 -> -81.980456 | I10: =-Calculations!$N$5/2 -> -300 | L10: =SUM(E10:K10) -> -991.07098 | M10: =L10/(1+$B$4/12)^D10 -> -961.85231
A11: SOT Year 5 | B11: =-Calculations!$C$5*0.85*0.0045 -> -122.4 | C11: 1 | D11: 7 | E11: =-Calculations!$D$5 -> -609.09053 | G11: =-Calculations!$L$5/12 -> -81.980456 | L11: =SUM(E11:K11) -> -691.07098 | M11: =L11/(1+$B$4/12)^D11 -> -667.36008
A12: SOT Year 6 | B12: =-Calculations!$C$5*0.85*0.0045 -> -122.4 | C12: 1 | D12: 8 | E12: =-Calculations!$D$5 -> -609.09053 | G12: =-Calculations!$L$5/12 -> -81.980456 | L12: =SUM(E12:K12) -> -691.07098 | M12: =L12/(1+$B$4/12)^D12 -> -664.03988
C13: 1 | D13: 9 | E13: =-Calculations!$D$5 -> -609.09053 | G13: =-Calculations!$L$5/12 -> -81.980456 | L13: =SUM(E13:K13) -> -691.07098 | M13: =L13/(1+$B$4/12)^D13 -> -660.7362
C14: 1 | D14: 10 | E14: =-Calculations!$D$5 -> -609.09053 | G14: =-Calculations!$L$5/12 -> -81.980456 | L14: =SUM(E14:K14) -> -691.07098 | M14: =L14/(1+$B$4/12)^D14 -> -657.44896
C15: 1 | D15: 11 | E15: =-Calculations!$D$5 -> -609.09053 | G15: =-Calculations!$L$5/12 -> -81.980456 | L15: =SUM(E15:K15) -> -691.07098 | M15: =L15/(1+$B$4/12)^D15 -> -654.17807
C16: 1 | D16: 12 | E16: =-Calculations!$D$5 -> -609.09053 | G16: =-Calculations!$L$5/12 -> -81.980456 | I16: =-Calculations!$N$5/2 -> -300 | L16: =SUM(E16:K16) -> -991.07098 | M16: =L16/(1+$B$4/12)^D16 -> -933.49505
C17: 2 | D17: 13 | E17: =-Calculations!$D$5 -> -609.09053 | G17: =-Calculations!$L$5/12 -> -81.980456 | H17: =sum(B6,B8) -> -469.37 | L17: =SUM(E17:K17) -> -1160.441 | M17: =L17/(1+$B$4/12)^D17 -> -1087.5876
C18: 2 | D18: 14 | E18: =-Calculations!$D$5 -> -609.09053 | G18: =-Calculations!$L$5/12 -> -81.980456 | L18: =SUM(E18:K18) -> -691.07098 | M18: =L18/(1+$B$4/12)^D18 -> -644.46271
C19: 2 | D19: 15 | E19: =-Calculations!$D$5 -> -609.09053 | G19: =-Calculations!$L$5/12 -> -81.980456 | L19: =SUM(E19:K19) -> -691.07098 | M19: =L19/(1+$B$4/12)^D19 -> -641.25643
C20: 2 | D20: 16 | E20: =-Calculations!$D$5 -> -609.09053 | G20: =-Calculations!$L$5/12 -> -81.980456 | L20: =SUM(E20:K20) -> -691.07098 | M20: =L20/(1+$B$4/12)^D20 -> -638.0661
C21: 2 | D21: 17 | E21: =-Calculations!$D$5 -> -609.09053 | G21: =-Calculations!$L$5/12 -> -81.980456 | L21: =SUM(E21:K21) -> -691.07098 | M21: =L21/(1+$B$4/12)^D21 -> -634.89164
C22: 2 | D22: 18 | E22: =-Calculations!$D$5 -> -609.09053 | G22: =-Calculations!$L$5/12 -> -81.980456 | I22: =-Calculations!$N$5/2 -> -300 | L22: =SUM(E22:K22) -> -991.07098 | M22: =L22/(1+$B$4/12)^D22 -> -905.97382
C23: 2 | D23: 19 | E23: =-Calculations!$D$5 -> -609.09053 | G23: =-Calculations!$L$5/12 -> -81.980456 | L23: =SUM(E23:K23) -> -691.07098 | M23: =L23/(1+$B$4/12)^D23 -> -628.59003
C24: 2 | D24: 20 | E24: =-Calculations!$D$5 -> -609.09053 | G24: =-Calculations!$L$5/12 -> -81.980456 | L24: =SUM(E24:K24) -> -691.07098 | M24: =L24/(1+$B$4/12)^D24 -> -625.46271
C25: 2 | D25: 21 | E25: =-Calculations!$D$5 -> -609.09053 | G25: =-Calculations!$L$5/12 -> -81.980456 | L25: =SUM(E25:K25) -> -691.07098 | M25: =L25/(1+$B$4/12)^D25 -> -622.35096
C26: 2 | D26: 22 | E26: =-Calculations!$D$5 -> -609.09053 | G26: =-Calculations!$L$5/12 -> -81.980456 | L26: =SUM(E26:K26) -> -691.07098 | M26: =L26/(1+$B$4/12)^D26 -> -619.25468
C27: 2 | D27: 23 | E27: =-Calculations!$D$5 -> -609.09053 | G27: =-Calculations!$L$5/12 -> -81.980456 | L27: =SUM(E27:K27) -> -691.07098 | M27: =L27/(1+$B$4/12)^D27 -> -616.17381
C28: 2 | D28: 24 | E28: =-Calculations!$D$5 -> -609.09053 | G28: =-Calculations!$L$5/12 -> -81.980456 | I28: =-Calculations!$N$5/2 -> -300 | L28: =SUM(E28:K28) -> -991.07098 | M28: =L28/(1+$B$4/12)^D28 -> -879.26397
C29: 3 | D29: 25 | E29: =-Calculations!$D$5 -> -609.09053 | G29: =-Calculations!$L$5/12 -> -81.980456 | H29: =sum(B9,B6) -> -387.77 | L29: =SUM(E29:K29) -> -1078.841 | M29: =L29/(1+$B$4/12)^D29 -> -952.37041
C30: 3 | D30: 26 | E30: =-Calculations!$D$5 -> -609.09053 | G30: =-Calculations!$L$5/12 -> -81.980456 | L30: =SUM(E30:K30) -> -691.07098 | M30: =L30/(1+$B$4/12)^D30 -> -607.02287
C31: 3 | D31: 27 | E31: =-Calculations!$D$5 -> -609.09053 | G31: =-Calculations!$L$5/12 -> -81.980456 | L31: =SUM(E31:K31) -> -691.07098 | M31: =L31/(1+$B$4/12)^D31 -> -604.00285
C32: 3 | D32: 28 | E32: =-Calculations!$D$5 -> -609.09053 | G32: =-Calculations!$L$5/12 -> -81.980456 | L32: =SUM(E32:K32) -> -691.07098 | M32: =L32/(1+$B$4/12)^D32 -> -600.99787
C33: 3 | D33: 29 | E33: =-Calculations!$D$5 -> -609.09053 | G33: =-Calculations!$L$5/12 -> -81.980456 | L33: =SUM(E33:K33) -> -691.07098 | M33: =L33/(1+$B$4/12)^D33 -> -598.00783
C34: 3 | D34: 30 | E34: =-Calculations!$D$5 -> -609.09053 | G34: =-Calculations!$L$5/12 -> -81.980456 | I34: =-Calculations!$N$5/2 -> -300 | L34: =SUM(E34:K34) -> -991.07098 | M34: =L34/(1+$B$4/12)^D34 -> -853.34158
C35: 3 | D35: 31 | E35: =-Calculations!$D$5 -> -609.09053 | G35: =-Calculations!$L$5/12 -> -81.980456 | L35: =SUM(E35:K35) -> -691.07098 | M35: =L35/(1+$B$4/12)^D35 -> -592.0723
C36: 3 | D36: 32 | E36: =-Calculations!$D$5 -> -609.09053 | G36: =-Calculations!$L$5/12 -> -81.980456 | L36: =SUM(E36:K36) -> -691.07098 | M36: =L36/(1+$B$4/12)^D36 -> -589.12667
C37: 3 | D37: 33 | E37: =-Calculations!$D$5 -> -609.09053 | G37: =-Calculations!$L$5/12 -> -81.980456 | L37: =SUM(E37:K37) -> -691.07098 | M37: =L37/(1+$B$4/12)^D37 -> -586.19569
C38: 3 | D38: 34 | E38: =-Calculations!$D$5 -> -609.09053 | G38: =-Calculations!$L$5/12 -> -81.980456 | L38: =SUM(E38:K38) -> -691.07098 | M38: =L38/(1+$B$4/12)^D38 -> -583.27929
C39: 3 | D39: 35 | E39: =-Calculations!$D$5 -> -609.09053 | G39: =-Calculations!$L$5/12 -> -81.980456 | L39: =SUM(E39:K39) -> -691.07098 | M39: =L39/(1+$B$4/12)^D39 -> -580.37741
C40: 3 | D40: 36 | E40: =-Calculations!$D$5 -> -609.09053 | G40: =-Calculations!$L$5/12 -> -81.980456 | I40: =-Calculations!$N$5/2 -> -300 | L40: =SUM(E40:K40) -> -991.07098 | M40: =L40/(1+$B$4/12)^D40 -> -828.18343
C41: 4 | D41: 37 | E41: =-Calculations!$D$5 -> -609.09053 | G41: =-Calculations!$L$5/12 -> -81.980456 | H41: =sum(B10,B6) -> -306.17 | L41: =SUM(E41:K41) -> -997.24098 | M41: =L41/(1+$B$4/12)^D41 -> -829.19339
C42: 4 | D42: 38 | E42: =-Calculations!$D$5 -> -609.09053 | G42: =-Calculations!$L$5/12 -> -81.980456 | L42: =SUM(E42:K42) -> -691.07098 | M42: =L42/(1+$B$4/12)^D42 -> -571.75808
C43: 4 | D43: 39 | E43: =-Calculations!$D$5 -> -609.09053 | G43: =-Calculations!$L$5/12 -> -81.980456 | L43: =SUM(E43:K43) -> -691.07098 | M43: =L43/(1+$B$4/12)^D43 -> -568.91351
C44: 4 | D44: 40 | E44: =-Calculations!$D$5 -> -609.09053 | G44: =-Calculations!$L$5/12 -> -81.980456 | L44: =SUM(E44:K44) -> -691.07098 | M44: =L44/(1+$B$4/12)^D44 -> -566.0831
C45: 4 | D45: 41 | E45: =-Calculations!$D$5 -> -609.09053 | G45: =-Calculations!$L$5/12 -> -81.980456 | L45: =SUM(E45:K45) -> -691.07098 | M45: =L45/(1+$B$4/12)^D45 -> -563.26676
C46: 4 | D46: 42 | E46: =-Calculations!$D$5 -> -609.09053 | G46: =-Calculations!$L$5/12 -> -81.980456 | I46: =-Calculations!$N$5/2 -> -300 | L46: =SUM(E46:K46) -> -991.07098 | M46: =L46/(1+$B$4/12)^D46 -> -803.76699
C47: 4 | D47: 43 | E47: =-Calculations!$D$5 -> -609.09053 | G47: =-Calculations!$L$5/12 -> -81.980456 | L47: =SUM(E47:K47) -> -691.07098 | M47: =L47/(1+$B$4/12)^D47 -> -557.67606
C48: 4 | D48: 44 | E48: =-Calculations!$D$5 -> -609.09053 | G48: =-Calculations!$L$5/12 -> -81.980456 | L48: =SUM(E48:K48) -> -691.07098 | M48: =L48/(1+$B$4/12)^D48 -> -554.90155
C49: 4 | D49: 45 | E49: =-Calculations!$D$5 -> -609.09053 | G49: =-Calculations!$L$5/12 -> -81.980456 | L49: =SUM(E49:K49) -> -691.07098 | M49: =L49/(1+$B$4/12)^D49 -> -552.14085
C50: 4 | D50: 46 | E50: =-Calculations!$D$5 -> -609.09053 | G50: =-Calculations!$L$5/12 -> -81.980456 | L50: =SUM(E50:K50) -> -691.07098 | M50: =L50/(1+$B$4/12)^D50 -> -549.39388
C51: 4 | D51: 47 | E51: =-Calculations!$D$5 -> -609.09053 | G51: =-Calculations!$L$5/12 -> -81.980456 | L51: =SUM(E51:K51) -> -691.07098 | M51: =L51/(1+$B$4/12)^D51 -> -546.66058
C52: 4 | D52: 48 | E52: =-Calculations!$D$5 -> -609.09053 | G52: =-Calculations!$L$5/12 -> -81.980456 | I52: =-Calculations!$N$5/2 -> -300 | L52: =SUM(E52:K52) -> -991.07098 | M52: =L52/(1+$B$4/12)^D52 -> -780.0704
C53: 5 | D53: 49 | E53: =-Calculations!$D$5 -> -609.09053 | G53: =-Calculations!$L$5/12 -> -81.980456 | H53: =sum(B11,B6) -> -183.77 | L53: =SUM(E53:K53) -> -874.84098 | M53: =L53/(1+$B$4/12)^D53 -> -685.16015
C54: 5 | D54: 50 | E54: =-Calculations!$D$5 -> -609.09053 | G54: =-Calculations!$L$5/12 -> -81.980456 | L54: =SUM(E54:K54) -> -691.07098 | M54: =L54/(1+$B$4/12)^D54 -> -538.54199
C55: 5 | D55: 51 | E55: =-Calculations!$D$5 -> -609.09053 | G55: =-Calculations!$L$5/12 -> -81.980456 | L55: =SUM(E55:K55) -> -691.07098 | M55: =L55/(1+$B$4/12)^D55 -> -535.86268
C56: 5 | D56: 52 | E56: =-Calculations!$D$5 -> -609.09053 | G56: =-Calculations!$L$5/12 -> -81.980456 | L56: =SUM(E56:K56) -> -691.07098 | M56: =L56/(1+$B$4/12)^D56 -> -533.19669
C57: 5 | D57: 53 | E57: =-Calculations!$D$5 -> -609.09053 | G57: =-Calculations!$L$5/12 -> -81.980456 | L57: =SUM(E57:K57) -> -691.07098 | M57: =L57/(1+$B$4/12)^D57 -> -530.54397
C58: 5 | D58: 54 | E58: =-Calculations!$D$5 -> -609.09053 | G58: =-Calculations!$L$5/12 -> -81.980456 | I58: =-Calculations!$N$5/2 -> -300 | L58: =SUM(E58:K58) -> -991.07098 | M58: =L58/(1+$B$4/12)^D58 -> -757.07242
C59: 5 | D59: 55 | E59: =-Calculations!$D$5 -> -609.09053 | G59: =-Calculations!$L$5/12 -> -81.980456 | L59: =SUM(E59:K59) -> -691.07098 | M59: =L59/(1+$B$4/12)^D59 -> -525.27806
C60: 5 | D60: 56 | E60: =-Calculations!$D$5 -> -609.09053 | G60: =-Calculations!$L$5/12 -> -81.980456 | L60: =SUM(E60:K60) -> -691.07098 | M60: =L60/(1+$B$4/12)^D60 -> -522.66474
C61: 5 | D61: 57 | E61: =-Calculations!$D$5 -> -609.09053 | G61: =-Calculations!$L$5/12 -> -81.980456 | L61: =SUM(E61:K61) -> -691.07098 | M61: =L61/(1+$B$4/12)^D61 -> -520.06442
C62: 5 | D62: 58 | E62: =-Calculations!$D$5 -> -609.09053 | G62: =-Calculations!$L$5/12 -> -81.980456 | L62: =SUM(E62:K62) -> -691.07098 | M62: =L62/(1+$B$4/12)^D62 -> -517.47703
C63: 5 | D63: 59 | E63: =-Calculations!$D$5 -> -609.09053 | G63: =-Calculations!$L$5/12 -> -81.980456 | L63: =SUM(E63:K63) -> -691.07098 | M63: =L63/(1+$B$4/12)^D63 -> -514.90252
C64: 5 | D64: 60 | E64: =-Calculations!$D$5 -> -609.09053 | G64: =-Calculations!$L$5/12 -> -81.980456 | I64: =-Calculations!$N$5/2 -> -300 | L64: =SUM(E64:K64) -> -991.07098 | M64: =L64/(1+$B$4/12)^D64 -> -734.75247
C65: 6 | D65: 61 | E65: =-Calculations!$D$5 -> -609.09053 | G65: =-Calculations!$L$5/12 -> -81.980456 | H65: =sum(B12,B6) -> -183.77 | L65: =SUM(E65:K65) -> -874.84098 | M65: =L65/(1+$B$4/12)^D65 -> -645.356
C66: 6 | D66: 62 | E66: =-Calculations!$D$5 -> -609.09053 | G66: =-Calculations!$L$5/12 -> -81.980456 | L66: =SUM(E66:K66) -> -691.07098 | M66: =L66/(1+$B$4/12)^D66 -> -507.25558
C67: 6 | D67: 63 | E67: =-Calculations!$D$5 -> -609.09053 | G67: =-Calculations!$L$5/12 -> -81.980456 | L67: =SUM(E67:K67) -> -691.07098 | M67: =L67/(1+$B$4/12)^D67 -> -504.73192
C68: 6 | D68: 64 | E68: =-Calculations!$D$5 -> -609.09053 | G68: =-Calculations!$L$5/12 -> -81.980456 | L68: =SUM(E68:K68) -> -691.07098 | M68: =L68/(1+$B$4/12)^D68 -> -502.22081
C69: 6 | D69: 65 | E69: =-Calculations!$D$5 -> -609.09053 | G69: =-Calculations!$L$5/12 -> -81.980456 | L69: =SUM(E69:K69) -> -691.07098 | M69: =L69/(1+$B$4/12)^D69 -> -499.7222
C70: 6 | D70: 66 | E70: =-Calculations!$D$5 -> -609.09053 | G70: =-Calculations!$L$5/12 -> -81.980456 | I70: =-Calculations!$N$5/2 -> -300 | L70: =SUM(E70:K70) -> -991.07098 | M70: =L70/(1+$B$4/12)^D70 -> -713.09056
C71: 6 | D71: 67 | E71: =-Calculations!$D$5 -> -609.09053 | G71: =-Calculations!$L$5/12 -> -81.980456 | L71: =SUM(E71:K71) -> -691.07098 | M71: =L71/(1+$B$4/12)^D71 -> -494.76221
C72: 6 | D72: 68 | E72: =-Calculations!$D$5 -> -609.09053 | G72: =-Calculations!$L$5/12 -> -81.980456 | L72: =SUM(E72:K72) -> -691.07098 | M72: =L72/(1+$B$4/12)^D72 -> -492.30071
C73: 6 | D73: 69 | E73: =-Calculations!$D$5 -> -609.09053 | G73: =-Calculations!$L$5/12 -> -81.980456 | L73: =SUM(E73:K73) -> -691.07098 | M73: =L73/(1+$B$4/12)^D73 -> -489.85145
C74: 6 | D74: 70 | E74: =-Calculations!$D$5 -> -609.09053 | G74: =-Calculations!$L$5/12 -> -81.980456 | L74: =SUM(E74:K74) -> -691.07098 | M74: =L74/(1+$B$4/12)^D74 -> -487.41438
C75: 6 | D75: 71 | E75: =-Calculations!$D$5 -> -609.09053 | G75: =-Calculations!$L$5/12 -> -81.980456 | L75: =SUM(E75:K75) -> -691.07098 | M75: =L75/(1+$B$4/12)^D75 -> -484.98943
C76: 6 | D76: 72 | E76: =-Calculations!$D$5 -> -609.09053 | G76: =-Calculations!$L$5/12 -> -81.980456 | I76: =-Calculations!$N$5/2 -> -300 | K76: =Calculations!Q5 -> 11200 | L76: =SUM(E76:K76) -> 10208.929 | M76: =L76/(1+$B$4/12)^D76 -> 7128.9199

Sheet NPV-PHEV
C1: Calculations
E2: 2024 Hyundai Sonata Plug-in Hybrid (PHEV)
C3: Year | D3: Month | E3: Loan | F3: Home Charger Install | G3: Fuel Cost | H3: Registration? | I3: Maintenance | J3: New Battery | K3: Salvage | L3: Sum | M3: PV | N3: NPV
A4: Discount Rate? | B4: =Calculations!$B$30 -> 0.06 | C4: 0 | D4: 0 | F4: =-Calculations!F6 -> -1140 | L4: =SUM(E4:K4) -> -1140 | M4: =L4/(1+$B$4/12)^D4 -> -1140 | N4: =sum(M4:M76) -> -44436.33
C5: 1 | D5: 1 | E5: =-Calculations!$D$6 -> -647.15869 | G5: =-Calculations!$L$6/12 -> -124.79244 | H5: =sum(B6:B7) -> -668.27 | L5: =SUM(E5:K5) -> -1440.2211 | M5: =L5/(1+$B$4/12)^D5 -> -1433.0558
A6: Registration Fees | B6: =-18-23-9-4-0.94-1.5-0.7-2-0.5-1-0.33-0.3-0.1 -> -61.37 | C6: 1 | D6: 2 | E6: =-Calculations!$D$6 -> -647.15869 | G6: =-Calculations!$L$6/12 -> -124.79244 | L6: =SUM(E6:K6) -> -771.95113 | M6: =L6/(1+$B$4/12)^D6 -> -764.28913
A7: SOT Year 1 | B7: =-Calculations!$C$6*0.85*0.021 -> -606.9 | C7: 1 | D7: 3 | E7: =-Calculations!$D$6 -> -647.15869 | G7: =-Calculations!$L$6/12 -> -124.79244 | L7: =SUM(E7:K7) -> -771.95113 | M7: =L7/(1+$B$4/12)^D7 -> -760.4867
A8: SOT Year 2 | B8: =-Calculations!$C$6*0.85*0.015 -> -433.5 | C8: 1 | D8: 4 | E8: =-Calculations!$D$6 -> -647.15869 | G8: =-Calculations!$L$6/12 -> -124.79244 | L8: =SUM(E8:K8) -> -771.95113 | M8: =L8/(1+$B$4/12)^D8 -> -756.70318
A9: SOT Year 3 | B9: =-Calculations!$C$6*0.85*0.012 -> -346.8 | C9: 1 | D9: 5 | E9: =-Calculations!$D$6 -> -647.15869 | G9: =-Calculations!$L$6/12 -> -124.79244 | L9: =SUM(E9:K9) -> -771.95113 | M9: =L9/(1+$B$4/12)^D9 -> -752.93849
A10: SOT Year 4 | B10: =-Calculations!$C$6*0.85*0.009 -> -260.1 | C10: 1 | D10: 6 | E10: =-Calculations!$D$6 -> -647.15869 | G10: =-Calculations!$L$6/12 -> -124.79244 | I10: =-Calculations!$N$6/2 -> -300 | L10: =SUM(E10:K10) -> -1071.9511 | M10: =L10/(1+$B$4/12)^D10 -> -1040.3479
A11: SOT Year 5 | B11: =-Calculations!$C$6*0.85*0.0045 -> -130.05 | C11: 1 | D11: 7 | E11: =-Calculations!$D$6 -> -647.15869 | G11: =-Calculations!$L$6/12 -> -124.79244 | L11: =SUM(E11:K11) -> -771.95113 | M11: =L11/(1+$B$4/12)^D11 -> -745.4652
A12: SOT Year 6 | B12: =-Calculations!$C$6*0.85*0.0045 -> -130.05 | C12: 1 | D12: 8 | E12: =-Calculations!$D$6 -> -647.15869 | G12: =-Calculations!$L$6/12 -> -124.79244 | L12: =SUM(E12:K12) -> -771.95113 | M12: =L12/(1+$B$4/12)^D12 -> -741.75642
C13: 1 | D13: 9 | E13: =-Calculations!$D$6 -> -647.15869 | G13: =-Calculations!$L$6/12 -> -124.79244 | L13: =SUM(E13:K13) -> -771.95113 | M13: =L13/(1+$B$4/12)^D13 -> -738.06609
C14: 1 | D14: 10 | E14: =-Calculations!$D$6 -> -647.15869 | G14: =-Calculations!$L$6/12 -> -124.79244 | L14: =SUM(E14:K14) -> -771.95113 | M14: =L14/(1+$B$4/12)^D14 -> -734.39412
C15: 1 | D15: 11 | E15: =-Calculations!$D$6 -> -647.15869 | G15: =-Calculations!$L$6/12 -> -124.79244 | L15: =SUM(E15:K15) -> -771.95113 | M15: =L15/(1+$B$4/12)^D15 -> -730.74041
C16: 1 | D16: 12 | E16: =-Calculations!$D$6 -> -647.15869 | G16: =-Calculations!$L$6/12 -> -124.79244 | I16: =-Calculations!$N$6/2 -> -300 | L16: =SUM(E16:K16) -> -1071.9511 | M16: =L16/(1+$B$4/12)^D16 -> -1009.6765
C17: 2 | D17: 13 | E17: =-Calculations!$D$6 -> -647.15869 | G17: =-Calculations!$L$6/12 -> -124.79244 | H17: =sum(B6,B8) -> -494.87 | L17: =SUM(E17:K17) -> -1266.8211 | M17: =L17/(1+$B$4/12)^D17 -> -1187.2891
C18: 2 | D18: 14 | E18: =-Calculations!$D$6 -> -647.15869 | G18: =-Calculations!$L$6/12 -> -124.79244 | L18: =SUM(E18:K18) -> -771.95113 | M18: =L18/(1+$B$4/12)^D18 -> -719.88801
C19: 2 | D19: 15 | E19: =-Calculations!$D$6 -> -647.15869 | G19: =-Calculations!$L$6/12 -> -124.79244 | L19: =SUM(E19:K19) -> -771.95113 | M19: =L19/(1+$B$4/12)^D19 -> -716.30648
C20: 2 | D20: 16 | E20: =-Calculations!$D$6 -> -647.15869 | G20: =-Calculations!$L$6/12 -> -124.79244 | L20: =SUM(E20:K20) -> -771.95113 | M20: =L20/(1+$B$4/12)^D20 -> -712.74277
C21: 2 | D21: 17 | E21: =-Calculations!$D$6 -> -647.15869 | G21: =-Calculations!$L$6/12 -> -124.79244 | L21: =SUM(E21:K21) -> -771.95113 | M21: =L21/(1+$B$4/12)^D21 -> -709.19678
C22: 2 | D22: 18 | E22: =-Calculations!$D$6 -> -647.15869 | G22: =-Calculations!$L$6/12 -> -124.79244 | I22: =-Calculations!$N$6/2 -> -300 | L22: =SUM(E22:K22) -> -1071.9511 | M22: =L22/(1+$B$4/12)^D22 -> -979.90929
C23: 2 | D23: 19 | E23: =-Calculations!$D$6 -> -647.15869 | G23: =-Calculations!$L$6/12 -> -124.79244 | L23: =SUM(E23:K23) -> -771.95113 | M23: =L23/(1+$B$4/12)^D23 -> -702.15765
C24: 2 | D24: 20 | E24: =-Calculations!$D$6 -> -647.15869 | G24: =-Calculations!$L$6/12 -> -124.79244 | L24: =SUM(E24:K24) -> -771.95113 | M24: =L24/(1+$B$4/12)^D24 -> -698.66433
C25: 2 | D25: 21 | E25: =-Calculations!$D$6 -> -647.15869 | G25: =-Calculations!$L$6/12 -> -124.79244 | L25: =SUM(E25:K25) -> -771.95113 | M25: =L25/(1+$B$4/12)^D25 -> -695.18839
C26: 2 | D26: 22 | E26: =-Calculations!$D$6 -> -647.15869 | G26: =-Calculations!$L$6/12 -> -124.79244 | L26: =SUM(E26:K26) -> -771.95113 | M26: =L26/(1+$B$4/12)^D26 -> -691.72974
C27: 2 | D27: 23 | E27: =-Calculations!$D$6 -> -647.15869 | G27: =-Calculations!$L$6/12 -> -124.79244 | L27: =SUM(E27:K27) -> -771.95113 | M27: =L27/(1+$B$4/12)^D27 -> -688.2883
C28: 2 | D28: 24 | E28: =-Calculations!$D$6 -> -647.15869 | G28: =-Calculations!$L$6/12 -> -124.79244 | I28: =-Calculations!$N$6/2 -> -300 | L28: =SUM(E28:K28) -> -1071.9511 | M28: =L28/(1+$B$4/12)^D28 -> -951.01968
C29: 3 | D29: 25 | E29: =-Calculations!$D$6 -> -647.15869 | G29: =-Calculations!$L$6/12 -> -124.79244 | H29: =sum(B9,B6) -> -408.17 | L29: =SUM(E29:K29) -> -1180.1211 | M29: =L29/(1+$B$4/12)^D29 -> -1041.7777
C30: 3 | D30: 26 | E30: =-Calculations!$D$6 -> -647.15869 | G30: =-Calculations!$L$6/12 -> -124.79244 | L30: =SUM(E30:K30) -> -771.95113 | M30: =L30/(1+$B$4/12)^D30 -> -678.06636
C31: 3 | D31: 27 | E31: =-Calculations!$D$6 -> -647.15869 | G31: =-Calculations!$L$6/12 -> -124.79244 | L31: =SUM(E31:K31) -> -771.95113 | M31: =L31/(1+$B$4/12)^D31 -> -674.6929
C32: 3 | D32: 28 | E32: =-Calculations!$D$6 -> -647.15869 | G32: =-Calculations!$L$6/12 -> -124.79244 | L32: =SUM(E32:K32) -> -771.95113 | M32: =L32/(1+$B$4/12)^D32 -> -671.33622
C33: 3 | D33: 29 | E33: =-Calculations!$D$6 -> -647.15869 | G33: =-Calculations!$L$6/12 -> -124.79244 | L33: =SUM(E33:K33) -> -771.95113 | M33: =L33/(1+$B$4/12)^D33 -> -667.99624
C34: 3 | D34: 30 | E34: =-Calculations!$D$6 -> -647.15869 | G34: =-Calculations!$L$6/12 -> -124.79244 | I34: =-Calculations!$N$6/2 -> -300 | L34: =SUM(E34:K34) -> -1071.9511 | M34: =L34/(1+$B$4/12)^D34 -> -922.98179
C35: 3 | D35: 31 | E35: =-Calculations!$D$6 -> -647.15869 | G35: =-Calculations!$L$6/12 -> -124.79244 | L35: =SUM(E35:K35) -> -771.95113 | M35: =L35/(1+$B$4/12)^D35 -> -661.36604
C36: 3 | D36: 32 | E36: =-Calculations!$D$6 -> -647.15869 | G36: =-Calculations!$L$6/12 -> -124.79244 | L36: =SUM(E36:K36) -> -771.95113 | M36: =L36/(1+$B$4/12)^D36 -> -658.07566
C37: 3 | D37: 33 | E37: =-Calculations!$D$6 -> -647.15869 | G37: =-Calculations!$L$6/12 -> -124.79244 | L37: =SUM(E37:K37) -> -771.95113 | M37: =L37/(1+$B$4/12)^D37 -> -654.80165
C38: 3 | D38: 34 | E38: =-Calculations!$D$6 -> -647.15869 | G38: =-Calculations!$L$6/12 -> -124.79244 | L38: =SUM(E38:K38) -> -771.95113 | M38: =L38/(1+$B$4/12)^D38 -> -651.54393
C39: 3 | D39: 35 | E39: =-Calculations!$D$6 -> -647.15869 | G39: =-Calculations!$L$6/12 -> -124.79244 | L39: =SUM(E39:K39) -> -771.95113 | M39: =L39/(1+$B$4/12)^D39 -> -648.30242
C40: 3 | D40: 36 | E40: =-Calculations!$D$6 -> -647.15869 | G40: =-Calculations!$L$6/12 -> -124.79244 | I40: =-Calculations!$N$6/2 -> -300 | L40: =SUM(E40:K40) -> -1071.9511 | M40: =L40/(1+$B$4/12)^D40 -> -895.77051
C41: 4 | D41: 37 | E41: =-Calculations!$D$6 -> -647.15869 | G41: =-Calculations!$L$6/12 -> -124.79244 | H41: =sum(B10,B6) -> -321.47 | L41: =SUM(E41:K41) -> -1093.4211 | M41: =L41/(1+$B$4/12)^D41 -> -909.16598
C42: 4 | D42: 38 | E42: =-Calculations!$D$6 -> -647.15869 | G42: =-Calculations!$L$6/12 -> -124.79244 | L42: =SUM(E42:K42) -> -771.95113 | M42: =L42/(1+$B$4/12)^D42 -> -638.67433
C43: 4 | D43: 39 | E43: =-Calculations!$D$6 -> -647.15869 | G43: =-Calculations!$L$6/12 -> -124.79244 | L43: =SUM(E43:K43) -> -771.95113 | M43: =L43/(1+$B$4/12)^D43 -> -635.49684
C44: 4 | D44: 40 | E44: =-Calculations!$D$6 -> -647.15869 | G44: =-Calculations!$L$6/12 -> -124.79244 | L44: =SUM(E44:K44) -> -771.95113 | M44: =L44/(1+$B$4/12)^D44 -> -632.33517
C45: 4 | D45: 41 | E45: =-Calculations!$D$6 -> -647.15869 | G45: =-Calculations!$L$6/12 -> -124.79244 | L45: =SUM(E45:K45) -> -771.95113 | M45: =L45/(1+$B$4/12)^D45 -> -629.18922
C46: 4 | D46: 42 | E46: =-Calculations!$D$6 -> -647.15869 | G46: =-Calculations!$L$6/12 -> -124.79244 | I46: =-Calculations!$N$6/2 -> -300 | L46: =SUM(E46:K46) -> -1071.9511 | M46: =L46/(1+$B$4/12)^D46 -> -869.36148
C47: 4 | D47: 43 | E47: =-Calculations!$D$6 -> -647.15869 | G47: =-Calculations!$L$6/12 -> -124.79244 | L47: =SUM(E47:K47) -> -771.95113 | M47: =L47/(1+$B$4/12)^D47 -> -622.94421
C48: 4 | D48: 44 | E48: =-Calculations!$D$6 -> -647.15869 | G48: =-Calculations!$L$6/12 -> -124.79244 | L48: =SUM(E48:K48) -> -771.95113 | M48: =L48/(1+$B$4/12)^D48 -> -619.84498
C49: 4 | D49: 45 | E49: =-Calculations!$D$6 -> -647.15869 | G49: =-Calculations!$L$6/12 -> -124.79244 | L49: =SUM(E49:K49) -> -771.95113 | M49: =L49/(1+$B$4/12)^D49 -> -616.76117
C50: 4 | D50: 46 | E50: =-Calculations!$D$6 -> -647.15869 | G50: =-Calculations!$L$6/12 -> -124.79244 | L50: =SUM(E50:K50) -> -771.95113 | M50: =L50/(1+$B$4/12)^D50 -> -613.69271
C51: 4 | D51: 47 | E51: =-Calculations!$D$6 -> -647.15869 | G51: =-Calculations!$L$6/12 -> -124.79244 | L51: =SUM(E51:K51) -> -771.95113 | M51: =L51/(1+$B$4/12)^D51 -> -610.63951
C52: 4 | D52: 48 | E52: =-Calculations!$D$6 -> -647.15869 | G52: =-Calculations!$L$6/12 -> -124.79244 | I52: =-Calculations!$N$6/2 -> -300 | L52: =SUM(E52:K52) -> -1071.9511 | M52: =L52/(1+$B$4/12)^D52 -> -843.73103
C53: 5 | D53: 49 | E53: =-Calculations!$D$6 -> -647.15869 | G53: =-Calculations!$L$6/12 -> -124.79244 | H53: =sum(B11,B6) -> -191.42 | L53: =SUM(E53:K53) -> -963.37113 | M53: =L53/(1+$B$4/12)^D53 -> -754.49541
C54: 5 | D54: 50 | E54: =-Calculations!$D$6 -> -647.15869 | G54: =-Calculations!$L$6/12 -> -124.79244 | L54: =SUM(E54:K54) -> -771.95113 | M54: =L54/(1+$B$4/12)^D54 -> -601.57076
C55: 5 | D55: 51 | E55: =-Calculations!$D$6 -> -647.15869 | G55: =-Calculations!$L$6/12 -> -124.79244 | L55: =SUM(E55:K55) -> -771.95113 | M55: =L55/(1+$B$4/12)^D55 -> -598.57787
C56: 5 | D56: 52 | E56: =-Calculations!$D$6 -> -647.15869 | G56: =-Calculations!$L$6/12 -> -124.79244 | L56: =SUM(E56:K56) -> -771.95113 | M56: =L56/(1+$B$4/12)^D56 -> -595.59987
C57: 5 | D57: 53 | E57: =-Calculations!$D$6 -> -647.15869 | G57: =-Calculations!$L$6/12 -> -124.79244 | L57: =SUM(E57:K57) -> -771.95113 | M57: =L57/(1+$B$4/12)^D57 -> -592.63669
C58: 5 | D58: 54 | E58: =-Calculations!$D$6 -> -647.15869 | G58: =-Calculations!$L$6/12 -> -124.79244 | I58: =-Calculations!$N$6/2 -> -300 | L58: =SUM(E58:K58) -> -1071.9511 | M58: =L58/(1+$B$4/12)^D58 -> -818.85622
C59: 5 | D59: 55 | E59: =-Calculations!$D$6 -> -647.15869 | G59: =-Calculations!$L$6/12 -> -124.79244 | L59: =SUM(E59:K59) -> -771.95113 | M59: =L59/(1+$B$4/12)^D59 -> -586.75447
C60: 5 | D60: 56 | E60: =-Calculations!$D$6 -> -647.15869 | G60: =-Calculations!$L$6/12 -> -124.79244 | L60: =SUM(E60:K60) -> -771.95113 | M60: =L60/(1+$B$4/12)^D60 -> -583.8353
C61: 5 | D61: 57 | E61: =-Calculations!$D$6 -> -647.15869 | G61: =-Calculations!$L$6/12 -> -124.79244 | L61: =SUM(E61:K61) -> -771.95113 | M61: =L61/(1+$B$4/12)^D61 -> -580.93064
C62: 5 | D62: 58 | E62: =-Calculations!$D$6 -> -647.15869 | G62: =-Calculations!$L$6/12 -> -124.79244 | L62: =SUM(E62:K62) -> -771.95113 | M62: =L62/(1+$B$4/12)^D62 -> -578.04044
C63: 5 | D63: 59 | E63: =-Calculations!$D$6 -> -647.15869 | G63: =-Calculations!$L$6/12 -> -124.79244 | L63: =SUM(E63:K63) -> -771.95113 | M63: =L63/(1+$B$4/12)^D63 -> -575.16462
C64: 5 | D64: 60 | E64: =-Calculations!$D$6 -> -647.15869 | G64: =-Calculations!$L$6/12 -> -124.79244 | I64: =-Calculations!$N$6/2 -> -300 | L64: =SUM(E64:K64) -> -1071.9511 | M64: =L64/(1+$B$4/12)^D64 -> -794.71476
C65: 6 | D65: 61 | E65: =-Calculations!$D$6 -> -647.15869 | G65: =-Calculations!$L$6/12 -> -124.79244 | H65: =sum(B12,B6) -> -191.42 | L65: =SUM(E65:K65) -> -963.37113 | M65: =L65/(1+$B$4/12)^D65 -> -710.66325
C66: 6 | D66: 62 | E66: =-Calculations!$D$6 -> -647.15869 | G66: =-Calculations!$L$6/12 -> -124.79244 | L66: =SUM(E66:K66) -> -771.95113 | M66: =L66/(1+$B$4/12)^D66 -> -566.62271
C67: 6 | D67: 63 | E67: =-Calculations!$D$6 -> -647.15869 | G67: =-Calculations!$L$6/12 -> -124.79244 | L67: =SUM(E67:K67) -> -771.95113 | M67: =L67/(1+$B$4/12)^D67 -> -563.80369
C68: 6 | D68: 64 | E68: =-Calculations!$D$6 -> -647.15869 | G68: =-Calculations!$L$6/12 -> -124.79244 | L68: =SUM(E68:K68) -> -771.95113 | M68: =L68/(1+$B$4/12)^D68 -> -560.9987
C69: 6 | D69: 65 | E69: =-Calculations!$D$6 -> -647.15869 | G69: =-Calculations!$L$6/12 -> -124.79244 | L69: =SUM(E69:K69) -> -771.95113 | M69: =L69/(1+$B$4/12)^D69 -> -558.20766
C70: 6 | D70: 66 | E70: =-Calculations!$D$6 -> -647.15869 | G70: =-Calculations!$L$6/12 -> -124.79244 | I70: =-Calculations!$N$6/2 -> -300 | L70: =SUM(E70:K70) -> -1071.9511 | M70: =L70/(1+$B$4/12)^D70 -> -771.28504
C71: 6 | D71: 67 | E71: =-Calculations!$D$6 -> -647.15869 | G71: =-Calculations!$L$6/12 -> -124.79244 | L71: =SUM(E71:K71) -> -771.95113 | M71: =L71/(1+$B$4/12)^D71 -> -552.66717
C72: 6 | D72: 68 | E72: =-Calculations!$D$6 -> -647.15869 | G72: =-Calculations!$L$6/12 -> -124.79244 | L72: =SUM(E72:K72) -> -771.95113 | M72: =L72/(1+$B$4/12)^D72 -> -549.91758
C73: 6 | D73: 69 | E73: =-Calculations!$D$6 -> -647.15869 | G73: =-Calculations!$L$6/12 -> -124.79244 | L73: =SUM(E73:K73) -> -771.95113 | M73: =L73/(1+$B$4/12)^D73 -> -547.18168
C74: 6 | D74: 70 | E74: =-Calculations!$D$6 -> -647.15869 | G74: =-Calculations!$L$6/12 -> -124.79244 | L74: =SUM(E74:K74) -> -771.95113 | M74: =L74/(1+$B$4/12)^D74 -> -544.45938
C75: 6 | D75: 71 | E75: =-Calculations!$D$6 -> -647.15869 | G75: =-Calculations!$L$6/12 -> -124.79244 | L75: =SUM(E75:K75) -> -771.95113 | M75: =L75/(1+$B$4/12)^D75 -> -541.75063
C76: 6 | D76: 72 | E76: =-Calculations!$D$6 -> -647.15869 | G76: =-Calculations!$L$6/12 -> -124.79244 | I76: =-Calculations!$N$6/2 -> -300 | K76: =Calculations!Q6 -> 11900 | L76: =SUM(E76:K76) -> 10828.049 | M76: =L76/(1+$B$4/12)^D76 -> 7561.2528

Sheet NPV-BEV
C1: Calculations
E2: 2024 Tesla Model 3 RWD (BEV)
C3: Year | D3: Month | E3: Loan | F3: Home Charger Install | G3: Fuel Cost | H3: Registration? | I3: Maintenance | J3: New Battery | K3: Salvage | L3: Sum | M3: PV | N3: NPV
A4: Discount Rate? | B4: =Calculations!$B$30 -> 0.06 | C4: 0 | D4: 0 | F4: =-Calculations!F7 -> -3000 | L4: =SUM(E4:K4) -> -3000 | M4: =L4/(1+$B$4/12)^D4 -> -3000 | N4: =sum(M4:M76) -> -32002.201
C5: 1 | D5: 1 | E5: =-Calculations!$D$7 -> -532.95421 | G5: =-Calculations!$L$7/12 -> -34.596774 | H5: =sum(B6:B7) -> -757.52 | L5: =SUM(E5:K5) -> -1325.071 | M5: =L5/(1+$B$4/12)^D5 -> -1318.4786
A6: Registration Fees | B6: =-18-23-9-4-0.94-1.5-0.7-2-0.5-1-0.33-0.3-0.1 -> -61.37 | C6: 1 | D6: 2 | E6: =-Calculations!$D$7 -> -532.95421 | G6: =-Calculations!$L$7/12 -> -34.596774 | L6: =SUM(E6:K6) -> -567.55099 | M6: =L6/(1+$B$4/12)^D6 -> -561.91776
A7: SOT Year 1 | B7: =-Calculations!$C$7*0.85*0.021 -> -696.15 | C7: 1 | D7: 3 | E7: =-Calculations!$D$7 -> -532.95421 | G7: =-Calculations!$L$7/12 -> -34.596774 | L7: =SUM(E7:K7) -> -567.55099 | M7: =L7/(1+$B$4/12)^D7 -> -559.12215
A8: SOT Year 2 | B8: =-Calculations!$C$7*0.85*0.015 -> -497.25 | C8: 1 | D8: 4 | E8: =-Calculations!$D$7 -> -532.95421 | G8: =-Calculations!$L$7/12 -> -34.596774 | L8: =SUM(E8:K8) -> -567.55099 | M8: =L8/(1+$B$4/12)^D8 -> -556.34045
A9: SOT Year 3 | B9: =-Calculations!$C$7*0.85*0.012 -> -397.8 | C9: 1 | D9: 5 | E9: =-Calculations!$D$7 -> -532.95421 | G9: =-Calculations!$L$7/12 -> -34.596774 | L9: =SUM(E9:K9) -> -567.55099 | M9: =L9/(1+$B$4/12)^D9 -> -553.57258
A10: SOT Year 4 | B10: =-Calculations!$C$7*0.85*0.009 -> -298.35 | C10: 1 | D10: 6 | E10: =-Calculations!$D$7 -> -532.95421 | G10: =-Calculations!$L$7/12 -> -34.596774 | I10: =-Calculations!$N$7/2 -> -200 | L10: =SUM(E10:K10) -> -767.55099 | M10: =L10/(1+$B$4/12)^D10 -> -744.92211
A11: SOT Year 5 | B11: =-Calculations!$C$7*0.85*0.0045 -> -149.175 | C11: 1 | D11: 7 | E11: =-Calculations!$D$7 -> -532.95421 | G11: =-Calculations!$L$7/12 -> -34.596774 | L11: =SUM(E11:K11) -> -567.55099 | M11: =L11/(1+$B$4/12)^D11 -> -548.0781
A12: SOT Year 6 | B12: =-Calculations!$C$7*0.85*0.0045 -> -149.175 | C12: 1 | D12: 8 | E12: =-Calculations!$D$7 -> -532.95421 | G12: =-Calculations!$L$7/12 -> -34.596774 | L12: =SUM(E12:K12) -> -567.55099 | M12: =L12/(1+$B$4/12)^D12 -> -545.35135
C13: 1 | D13: 9 | E13: =-Calculations!$D$7 -> -532.95421 | G13: =-Calculations!$L$7/12 -> -34.596774 | L13: =SUM(E13:K13) -> -567.55099 | M13: =L13/(1+$B$4/12)^D13 -> -542.63815
C14: 1 | D14: 10 | E14: =-Calculations!$D$7 -> -532.95421 | G14: =-Calculations!$L$7/12 -> -34.596774 | L14: =SUM(E14:K14) -> -567.55099 | M14: =L14/(1+$B$4/12)^D14 -> -539.93846
C15: 1 | D15: 11 | E15: =-Calculations!$D$7 -> -532.95421 | G15: =-Calculations!$L$7/12 -> -34.596774 | L15: =SUM(E15:K15) -> -567.55099 | M15: =L15/(1+$B$4/12)^D15 -> -537.2522
C16: 1 | D16: 12 | E16: =-Calculations!$D$7 -> -532.95421 | G16: =-Calculations!$L$7/12 -> -34.596774 | I16: =-Calculations!$N$7/2 -> -200 | L16: =SUM(E16:K16) -> -767.55099 | M16: =L16/(1+$B$4/12)^D16 -> -722.96037
C17: 2 | D17: 13 | E17: =-Calculations!$D$7 -> -532.95421 | G17: =-Calculations!$L$7/12 -> -34.596774 | H17: =sum(B6,B8) -> -558.62 | L17: =SUM(E17:K17) -> -1126.171 | M17: =L17/(1+$B$4/12)^D17 -> -1055.4691
C18: 2 | D18: 14 | E18: =-Calculations!$D$7 -> -532.95421 | G18: =-Calculations!$L$7/12 -> -34.596774 | L18: =SUM(E18:K18) -> -567.55099 | M18: =L18/(1+$B$4/12)^D18 -> -529.27334
C19: 2 | D19: 15 | E19: =-Calculations!$D$7 -> -532.95421 | G19: =-Calculations!$L$7/12 -> -34.596774 | L19: =SUM(E19:K19) -> -567.55099 | M19: =L19/(1+$B$4/12)^D19 -> -526.64014
C20: 2 | D20: 16 | E20: =-Calculations!$D$7 -> -532.95421 | G20: =-Calculations!$L$7/12 -> -34.596774 | L20: =SUM(E20:K20) -> -567.55099 | M20: =L20/(1+$B$4/12)^D20 -> -524.02004
C21: 2 | D21: 17 | E21: =-Calculations!$D$7 -> -532.95421 | G21: =-Calculations!$L$7/12 -> -34.596774 | L21: =SUM(E21:K21) -> -567.55099 | M21: =L21/(1+$B$4/12)^D21 -> -521.41297
C22: 2 | D22: 18 | E22: =-Calculations!$D$7 -> -532.95421 | G22: =-Calculations!$L$7/12 -> -34.596774 | I22: =-Calculations!$N$7/2 -> -200 | L22: =SUM(E22:K22) -> -767.55099 | M22: =L22/(1+$B$4/12)^D22 -> -701.64611
C23: 2 | D23: 19 | E23: =-Calculations!$D$7 -> -532.95421 | G23: =-Calculations!$L$7/12 -> -34.596774 | L23: =SUM(E23:K23) -> -567.55099 | M23: =L23/(1+$B$4/12)^D23 -> -516.23769
C24: 2 | D24: 20 | E24: =-Calculations!$D$7 -> -532.95421 | G24: =-Calculations!$L$7/12 -> -34.596774 | L24: =SUM(E24:K24) -> -567.55099 | M24: =L24/(1+$B$4/12)^D24 -> -513.66934
C25: 2 | D25: 21 | E25: =-Calculations!$D$7 -> -532.95421 | G25: =-Calculations!$L$7/12 -> -34.596774 | L25: =SUM(E25:K25) -> -567.55099 | M25: =L25/(1+$B$4/12)^D25 -> -511.11377
C26: 2 | D26: 22 | E26: =-Calculations!$D$7 -> -532.95421 | G26: =-Calculations!$L$7/12 -> -34.596774 | L26: =SUM(E26:K26) -> -567.55099 | M26: =L26/(1+$B$4/12)^D26 -> -508.57092
C27: 2 | D27: 23 | E27: =-Calculations!$D$7 -> -532.95421 | G27: =-Calculations!$L$7/12 -> -34.596774 | L27: =SUM(E27:K27) -> -567.55099 | M27: =L27/(1+$B$4/12)^D27 -> -506.04072
C28: 2 | D28: 24 | E28: =-Calculations!$D$7 -> -532.95421 | G28: =-Calculations!$L$7/12 -> -34.596774 | I28: =-Calculations!$N$7/2 -> -200 | L28: =SUM(E28:K28) -> -767.55099 | M28: =L28/(1+$B$4/12)^D28 -> -680.96024
C29: 3 | D29: 25 | E29: =-Calculations!$D$7 -> -532.95421 | G29: =-Calculations!$L$7/12 -> -34.596774 | H29: =sum(B9,B6) -> -459.17 | L29: =SUM(E29:K29) -> -1026.721 | M29: =L29/(1+$B$4/12)^D29 -> -906.36034
C30: 3 | D30: 26 | E30: =-Calculations!$D$7 -> -532.95421 | G30: =-Calculations!$L$7/12 -> -34.596774 | L30: =SUM(E30:K30) -> -567.55099 | M30: =L30/(1+$B$4/12)^D30 -> -498.52538
C31: 3 | D31: 27 | E31: =-Calculations!$D$7 -> -532.95421 | G31: =-Calculations!$L$7/12 -> -34.596774 | L31: =SUM(E31:K31) -> -567.55099 | M31: =L31/(1+$B$4/12)^D31 -> -496.04516
C32: 3 | D32: 28 | E32: =-Calculations!$D$7 -> -532.95421 | G32: =-Calculations!$L$7/12 -> -34.596774 | L32: =SUM(E32:K32) -> -567.55099 | M32: =L32/(1+$B$4/12)^D32 -> -493.57727
C33: 3 | D33: 29 | E33: =-Calculations!$D$7 -> -532.95421 | G33: =-Calculations!$L$7/12 -> -34.596774 | L33: =SUM(E33:K33) -> -567.55099 | M33: =L33/(1+$B$4/12)^D33 -> -491.12166
C34: 3 | D34: 30 | E34: =-Calculations!$D$7 -> -532.95421 | G34: =-Calculations!$L$7/12 -> -34.596774 | I34: =-Calculations!$N$7/2 -> -200 | L34: =SUM(E34:K34) -> -767.55099 | M34: =L34/(1+$B$4/12)^D34 -> -660.88422
C35: 3 | D35: 31 | E35: =-Calculations!$D$7 -> -532.95421 | G35: =-Calculations!$L$7/12 -> -34.596774 | L35: =SUM(E35:K35) -> -567.55099 | M35: =L35/(1+$B$4/12)^D35 -> -486.24704
C36: 3 | D36: 32 | E36: =-Calculations!$D$7 -> -532.95421 | G36: =-Calculations!$L$7/12 -> -34.596774 | L36: =SUM(E36:K36) -> -567.55099 | M36: =L36/(1+$B$4/12)^D36 -> -483.8279
C37: 3 | D37: 33 | E37: =-Calculations!$D$7 -> -532.95421 | G37: =-Calculations!$L$7/12 -> -34.596774 | L37: =SUM(E37:K37) -> -567.55099 | M37: =L37/(1+$B$4/12)^D37 -> -481.42079
C38: 3 | D38: 34 | E38: =-Calculations!$D$7 -> -532.95421 | G38: =-Calculations!$L$7/12 -> -34.596774 | L38: =SUM(E38:K38) -> -567.55099 | M38: =L38/(1+$B$4/12)^D38 -> -479.02567
C39: 3 | D39: 35 | E39: =-Calculations!$D$7 -> -532.95421 | G39: =-Calculations!$L$7/12 -> -34.596774 | L39: =SUM(E39:K39) -> -567.55099 | M39: =L39/(1+$B$4/12)^D39 -> -476.64245
C40: 3 | D40: 36 | E40: =-Calculations!$D$7 -> -532.95421 | G40: =-Calculations!$L$7/12 -> -34.596774 | I40: =-Calculations!$N$7/2 -> -200 | L40: =SUM(E40:K40) -> -767.55099 | M40: =L40/(1+$B$4/12)^D40 -> -641.40008
C41: 4 | D41: 37 | E41: =-Calculations!$D$7 -> -532.95421 | G41: =-Calculations!$L$7/12 -> -34.596774 | H41: =sum(B10,B6) -> -359.72 | L41: =SUM(E41:K41) -> -927.27099 | M41: =L41/(1+$B$4/12)^D41 -> -771.01422
C42: 4 | D42: 38 | E42: =-Calculations!$D$7 -> -532.95421 | G42: =-Calculations!$L$7/12 -> -34.596774 | L42: =SUM(E42:K42) -> -567.55099 | M42: =L42/(1+$B$4/12)^D42 -> -469.56372
C43: 4 | D43: 39 | E43: =-Calculations!$D$7 -> -532.95421 | G43: =-Calculations!$L$7/12 -> -34.596774 | L43: =SUM(E43:K43) -> -567.55099 | M43: =L43/(1+$B$4/12)^D43 -> -467.22758
C44: 4 | D44: 40 | E44: =-Calculations!$D$7 -> -532.95421 | G44: =-Calculations!$L$7/12 -> -34.596774 | L44: =SUM(E44:K44) -> -567.55099 | M44: =L44/(1+$B$4/12)^D44 -> -464.90307
C45: 4 | D45: 41 | E45: =-Calculations!$D$7 -> -532.95421 | G45: =-Calculations!$L$7/12 -> -34.596774 | L45: =SUM(E45:K45) -> -567.55099 | M45: =L45/(1+$B$4/12)^D45 -> -462.59012
C46: 4 | D46: 42 | E46: =-Calculations!$D$7 -> -532.95421 | G46: =-Calculations!$L$7/12 -> -34.596774 | I46: =-Calculations!$N$7/2 -> -200 | L46: =SUM(E46:K46) -> -767.55099 | M46: =L46/(1+$B$4/12)^D46 -> -622.49037
C47: 4 | D47: 43 | E47: =-Calculations!$D$7 -> -532.95421 | G47: =-Calculations!$L$7/12 -> -34.596774 | L47: =SUM(E47:K47) -> -567.55099 | M47: =L47/(1+$B$4/12)^D47 -> -457.99868
C48: 4 | D48: 44 | E48: =-Calculations!$D$7 -> -532.95421 | G48: =-Calculations!$L$7/12 -> -34.596774 | L48: =SUM(E48:K48) -> -567.55099 | M48: =L48/(1+$B$4/12)^D48 -> -455.72008
C49: 4 | D49: 45 | E49: =-Calculations!$D$7 -> -532.95421 | G49: =-Calculations!$L$7/12 -> -34.596774 | L49: =SUM(E49:K49) -> -567.55099 | M49: =L49/(1+$B$4/12)^D49 -> -453.45282
C50: 4 | D50: 46 | E50: =-Calculations!$D$7 -> -532.95421 | G50: =-Calculations!$L$7/12 -> -34.596774 | L50: =SUM(E50:K50) -> -567.55099 | M50: =L50/(1+$B$4/12)^D50 -> -451.19683
C51: 4 | D51: 47 | E51: =-Calculations!$D$7 -> -532.95421 | G51: =-Calculations!$L$7/12 -> -34.596774 | L51: =SUM(E51:K51) -> -567.55099 | M51: =L51/(1+$B$4/12)^D51 -> -448.95207
C52: 4 | D52: 48 | E52: =-Calculations!$D$7 -> -532.95421 | G52: =-Calculations!$L$7/12 -> -34.596774 | I52: =-Calculations!$N$7/2 -> -200 | L52: =SUM(E52:K52) -> -767.55099 | M52: =L52/(1+$B$4/12)^D52 -> -604.13816
C53: 5 | D53: 49 | E53: =-Calculations!$D$7 -> -532.95421 | G53: =-Calculations!$L$7/12 -> -34.596774 | H53: =sum(B11,B6) -> -210.545 | L53: =SUM(E53:K53) -> -778.09599 | M53: =L53/(1+$B$4/12)^D53 -> -609.39116
C54: 5 | D54: 50 | E54: =-Calculations!$D$7 -> -532.95421 | G54: =-Calculations!$L$7/12 -> -34.596774 | L54: =SUM(E54:K54) -> -567.55099 | M54: =L54/(1+$B$4/12)^D54 -> -442.28458
C55: 5 | D55: 51 | E55: =-Calculations!$D$7 -> -532.95421 | G55: =-Calculations!$L$7/12 -> -34.596774 | L55: =SUM(E55:K55) -> -567.55099 | M55: =L55/(1+$B$4/12)^D55 -> -440.08416
C56: 5 | D56: 52 | E56: =-Calculations!$D$7 -> -532.95421 | G56: =-Calculations!$L$7/12 -> -34.596774 | L56: =SUM(E56:K56) -> -567.55099 | M56: =L56/(1+$B$4/12)^D56 -> -437.89468
C57: 5 | D57: 53 | E57: =-Calculations!$D$7 -> -532.95421 | G57: =-Calculations!$L$7/12 -> -34.596774 | L57: =SUM(E57:K57) -> -567.55099 | M57: =L57/(1+$B$4/12)^D57 -> -435.7161
C58: 5 | D58: 54 | E58: =-Calculations!$D$7 -> -532.95421 | G58: =-Calculations!$L$7/12 -> -34.596774 | I58: =-Calculations!$N$7/2 -> -200 | L58: =SUM(E58:K58) -> -767.55099 | M58: =L58/(1+$B$4/12)^D58 -> -586.32701
C59: 5 | D59: 55 | E59: =-Calculations!$D$7 -> -532.95421 | G59: =-Calculations!$L$7/12 -> -34.596774 | L59: =SUM(E59:K59) -> -567.55099 | M59: =L59/(1+$B$4/12)^D59 -> -431.3914
C60: 5 | D60: 56 | E60: =-Calculations!$D$7 -> -532.95421 | G60: =-Calculations!$L$7/12 -> -34.596774 | L60: =SUM(E60:K60) -> -567.55099 | M60: =L60/(1+$B$4/12)^D60 -> -429.24518
C61: 5 | D61: 57 | E61: =-Calculations!$D$7 -> -532.95421 | G61: =-Calculations!$L$7/12 -> -34.596774 | L61: =SUM(E61:K61) -> -567.55099 | M61: =L61/(1+$B$4/12)^D61 -> -427.10963
C62: 5 | D62: 58 | E62: =-Calculations!$D$7 -> -532.95421 | G62: =-Calculations!$L$7/12 -> -34.596774 | L62: =SUM(E62:K62) -> -567.55099 | M62: =L62/(1+$B$4/12)^D62 -> -424.98471
C63: 5 | D63: 59 | E63: =-Calculations!$D$7 -> -532.95421 | G63: =-Calculations!$L$7/12 -> -34.596774 | L63: =SUM(E63:K63) -> -567.55099 | M63: =L63/(1+$B$4/12)^D63 -> -422.87035
C64: 5 | D64: 60 | E64: =-Calculations!$D$7 -> -532.95421 | G64: =-Calculations!$L$7/12 -> -34.596774 | I64: =-Calculations!$N$7/2 -> -200 | L64: =SUM(E64:K64) -> -767.55099 | M64: =L64/(1+$B$4/12)^D64 -> -569.04096
C65: 6 | D65: 61 | E65: =-Calculations!$D$7 -> -532.95421 | G65: =-Calculations!$L$7/12 -> -34.596774 | H65: =sum(B12,B6) -> -210.545 | L65: =SUM(E65:K65) -> -778.09599 | M65: =L65/(1+$B$4/12)^D65 -> -573.98879
C66: 6 | D66: 62 | E66: =-Calculations!$D$7 -> -532.95421 | G66: =-Calculations!$L$7/12 -> -34.596774 | L66: =SUM(E66:K66) -> -567.55099 | M66: =L66/(1+$B$4/12)^D66 -> -416.5902
C67: 6 | D67: 63 | E67: =-Calculations!$D$7 -> -532.95421 | G67: =-Calculations!$L$7/12 -> -34.596774 | L67: =SUM(E67:K67) -> -567.55099 | M67: =L67/(1+$B$4/12)^D67 -> -414.51762
C68: 6 | D68: 64 | E68: =-Calculations!$D$7 -> -532.95421 | G68: =-Calculations!$L$7/12 -> -34.596774 | L68: =SUM(E68:K68) -> -567.55099 | M68: =L68/(1+$B$4/12)^D68 -> -412.45534
C69: 6 | D69: 65 | E69: =-Calculations!$D$7 -> -532.95421 | G69: =-Calculations!$L$7/12 -> -34.596774 | L69: =SUM(E69:K69) -> -567.55099 | M69: =L69/(1+$B$4/12)^D69 -> -410.40332
C70: 6 | D70: 66 | E70: =-Calculations!$D$7 -> -532.95421 | G70: =-Calculations!$L$7/12 -> -34.596774 | I70: =-Calculations!$N$7/2 -> -200 | L70: =SUM(E70:K70) -> -767.55099 | M70: =L70/(1+$B$4/12)^D70 -> -552.26454
C71: 6 | D71: 67 | E71: =-Calculations!$D$7 -> -532.95421 | G71: =-Calculations!$L$7/12 -> -34.596774 | L71: =SUM(E71:K71) -> -567.55099 | M71: =L71/(1+$B$4/12)^D71 -> -406.32987
C72: 6 | D72: 68 | E72: =-Calculations!$D$7 -> -532.95421 | G72: =-Calculations!$L$7/12 -> -34.596774 | L72: =SUM(E72:K72) -> -567.55099 | M72: =L72/(1+$B$4/12)^D72 -> -404.30832
C73: 6 | D73: 69 | E73: =-Calculations!$D$7 -> -532.95421 | G73: =-Calculations!$L$7/12 -> -34.596774 | L73: =SUM(E73:K73) -> -567.55099 | M73: =L73/(1+$B$4/12)^D73 -> -402.29684
C74: 6 | D74: 70 | E74: =-Calculations!$D$7 -> -532.95421 | G74: =-Calculations!$L$7/12 -> -34.596774 | L74: =SUM(E74:K74) -> -567.55099 | M74: =L74/(1+$B$4/12)^D74 -> -400.29536
C75: 6 | D75: 71 | E75: =-Calculations!$D$7 -> -532.95421 | G75: =-Calculations!$L$7/12 -> -34.596774 | L75: =SUM(E75:K75) -> -567.55099 | M75: =L75/(1+$B$4/12)^D75 -> -398.30384
C76: 6 | D76: 72 | E76: =-Calculations!$D$7 -> -532.95421 | G76: =-Calculations!$L$7/12 -> -34.596774 | I76: =-Calculations!$N$7/2 -> -200 | K76: =Calculations!Q7 -> 13650 | L76: =SUM(E76:K76) -> 12882.449 | M76: =L76/(1+$B$4/12)^D76 -> 8995.8455

Sheet Risk Graphs
A1: Fit Analysis for Purchase Price Std Dev
A25: Final NPV for each vehicle plotted, further right is better
A61: Ex. Chart: For each salvage value I put on a normal distribution where the std dev is about 10% of the nominal value, this shows that we may not necessarily get the full value when selling the car, or maybe we get lucky and find a sucker who will overpay
A86: Ex. Chart: I applied the "Pert" distribution to each annual maintenance cost, maybe get unlucky and need some new tires or other high ticket items at a regular service
A113: Ex. Chart: I used another Pert distribution to consider that the manufacturer lied to me and we will likely get worse range from each vehicle, i used the same offsets for each vehicle, max is +20 from nominal, and min is -60 from nominal
A138: Ex. Chart: Used a typical uniform chart for all fuel/electricity costs, considered prices may dip to 3.10 or jump up to 4 in this example, this is just to conisder that prices can go up or down throughout time but may end up hovering overall
A163: Ex. Chart: Used another uniform chart for the vehicle loan interest rate, varying rate between 9.9 and 12.1%
A188: Ex. Chart: Another uniform series on the amount of days we commute to work, from 240-260, maybe we take some sick days or go on vacation?
A212: Ex. Chart: Applied a normal distribution to the weekend travel range, because not every trip is the same.
A237: Ex. Chart: Another Pert series on weekend trips, this could have been a normal distribution, but maybe we err on the side of a few plans getting canceled throughout a year
A262: The effects of our travel and gas variables on the annual fuel cost, further left is better!
